{"de-de_about_community.md":"fpBibmWa","de-de_about_contact.md":"V-e2snZb","de-de_about_contribute_docs.md":"K8IZaYyO","de-de_about_contribute_structure.md":"DTt9Tzi2","de-de_about_events.md":"DOzgr8Nq","de-de_about_faq.md":"C3lr71km","de-de_about_history.md":"BJ9w1QAZ","de-de_about_license.md":"CbnmM32i","de-de_about_migration.md":"BOuXHBSV","de-de_about_releases.md":"D3ekfIPv","de-de_about_releases_v4.1.md":"DXa_2QVY","de-de_about_releases_v4.10.md":"BRixkP46","de-de_about_releases_v4.11.md":"BcwF4pDI","de-de_about_releases_v4.12.md":"DRkKBHA3","de-de_about_releases_v4.13.md":"V6cZhf5A","de-de_about_releases_v4.14.md":"Bium-9B6","de-de_about_releases_v4.15.md":"YukY3iQn","de-de_about_releases_v4.2.md":"CIPk434A","de-de_about_releases_v4.3.md":"BssNhOyj","de-de_about_releases_v4.4.md":"CtvbyGmn","de-de_about_releases_v4.5.md":"BW5M-nRo","de-de_about_releases_v4.6.md":"C9T_Uhvm","de-de_about_releases_v4.7.md":"JfaCoEAE","de-de_about_releases_v4.8.md":"ba2x_Yxs","de-de_about_releases_v4.9.md":"8reZMJ42","de-de_about_team.md":"CrynmDzg","de-de_about_upgrade.md":"BqpT8Mjb","de-de_api_console_component.md":"DgDqYMD3","de-de_api_console_composition.md":"CIqBAZTN","de-de_api_console_context.md":"CK7i_5Ut","de-de_api_console_server.md":"BIoznVHV","de-de_api_core_adapter.md":"BSwQt8jq","de-de_api_core_app.md":"DDrmxGBU","de-de_api_core_bot.md":"B6Kgqylw","de-de_api_core_command.md":"DF6p88lY","de-de_api_core_context.md":"BnA-AbHX","de-de_api_core_events.md":"Bioxayhn","de-de_api_core_session.md":"yFAsYMIw","de-de_api_database_built-in.md":"BilDqeR3","de-de_api_database_database.md":"D8TO4lvm","de-de_api_database_evaluation.md":"DUyeWUiH","de-de_api_database_model.md":"B0Og6FoS","de-de_api_database_query.md":"BrYPF5FU","de-de_api_database_selection.md":"B6nIIqJP","de-de_api_glossary.md":"DKC7UUAw","de-de_api_index.md":"Cyqe-Lq_","de-de_api_message_api.md":"CsHctpjh","de-de_api_message_components.md":"BlJ4uECD","de-de_api_message_elements.md":"BocCcYGF","de-de_api_message_encoder.md":"BvX-rxv7","de-de_api_message_syntax.md":"CRcsnz0d","de-de_api_platform_channel.md":"O2_Hr9D9","de-de_api_platform_guild.md":"B7giRTTp","de-de_api_platform_member.md":"BQVzunm_","de-de_api_platform_message.md":"BRFjhCoD","de-de_api_platform_reaction.md":"itYjNMy-","de-de_api_platform_role.md":"CEbVjPou","de-de_api_platform_user.md":"0apknpov","de-de_api_resources_channel.md":"DcwDj0tX","de-de_api_resources_guild.md":"n4N4jXnN","de-de_api_resources_interaction.md":"0oZuOfgz","de-de_api_resources_login.md":"B8MpcL11","de-de_api_resources_member.md":"DJVQd3xV","de-de_api_resources_message.md":"lJl4cen0","de-de_api_resources_reaction.md":"DghVvrqX","de-de_api_resources_role.md":"Brnr9Olv","de-de_api_resources_user.md":"mqVRIALw","de-de_api_service_bots.md":"BeAha5b_","de-de_api_service_events.md":"BsuclJjT","de-de_api_service_filter.md":"BTugu7Tt","de-de_api_service_http.md":"CxQ6plVk","de-de_api_service_i18n.md":"D5riJ3kK","de-de_api_service_lifecycle.md":"BgHSBy3M","de-de_api_service_loader.md":"CRhj1AzJ","de-de_api_service_logger.md":"tP5FAPig","de-de_api_service_permissions.md":"Boq_7hN5","de-de_api_service_registry.md":"WyRZq402","de-de_api_service_router.md":"DDvh7Jn7","de-de_api_service_selector.md":"BHFe2aTT","de-de_api_utils_logger.md":"BbyR40Q6","de-de_api_utils_misc.md":"D137hKUA","de-de_api_utils_observer.md":"brUDfOqK","de-de_api_utils_random.md":"BrgHlawL","de-de_api_utils_schema.md":"B8doijfC","de-de_cookbook_appendix_commands.md":"DNvoTQC3","de-de_cookbook_assets.md":"CpdgK8Zp","de-de_cookbook_design_bundle.md":"m5kwCBG-","de-de_cookbook_design_disposable.md":"BWaKjuyX","de-de_cookbook_design_framework.md":"CTYQt75R","de-de_cookbook_design_reversible.md":"ClxEM2nw","de-de_cookbook_design_storage.md":"MRrJsUtx","de-de_cookbook_design_structure.md":"CvGmx6hg","de-de_cookbook_design_workspace.md":"CPVG7isb","de-de_cookbook_index.md":"BaURZuM3","de-de_cookbook_message.md":"DUTrWXO_","de-de_cookbook_online.md":"CD524X8P","de-de_cookbook_practice_assets.md":"uo271hOF","de-de_cookbook_practice_bundle.md":"DYLXGfoI","de-de_cookbook_practice_online.md":"DCcp0FCC","de-de_cookbook_practice_render.md":"BU5ctWKj","de-de_cookbook_practice_testing.md":"bKr81bAb","de-de_cookbook_render.md":"DneMgSjL","de-de_cookbook_storage.md":"CWVrpMZR","de-de_cookbook_testing.md":"D1FfHtbf","de-de_guide_adapter_adapter.md":"p_36jJYr","de-de_guide_adapter_bot.md":"BIO4EORK","de-de_guide_adapter_index.md":"JswXHkmw","de-de_guide_adapter_integration.md":"CvODFSe_","de-de_guide_adapter_message.md":"DhDeL2t6","de-de_guide_basic_advanced.md":"BmQmInLa","de-de_guide_basic_command.md":"C5-l0gA-","de-de_guide_basic_element.md":"CKL6XXPd","de-de_guide_basic_events.md":"Cf00yS1v","de-de_guide_basic_middleware.md":"DU3Pu1sX","de-de_guide_console_client.md":"BYD8zeqC","de-de_guide_console_data.md":"BcAqafRx","de-de_guide_console_index.md":"DEs5x-zF","de-de_guide_console_theme.md":"Cn_ckOWz","de-de_guide_database_builtin.md":"ByCE7nyX","de-de_guide_database_index.md":"CiDe38Qk","de-de_guide_database_model.md":"DLY9O3ay","de-de_guide_database_observer.md":"CGxcxy-J","de-de_guide_database_permission.md":"h3HC9-Xu","de-de_guide_database_select.md":"BpD3hTZu","de-de_guide_database_selection.md":"HAJe5C-z","de-de_guide_database_writing.md":"-tjGV8MG","de-de_guide_develop_config.md":"DM4MkivU","de-de_guide_develop_publish.md":"DG0Mz7ki","de-de_guide_develop_script.md":"CDHyiLkK","de-de_guide_develop_setup.md":"BCcDVK1e","de-de_guide_develop_workspace.md":"TFfQjST9","de-de_guide_i18n_crowdin.md":"Dx4cBAva","de-de_guide_i18n_index.md":"Dieh35CU","de-de_guide_i18n_lang-pack.md":"B4UOAGcH","de-de_guide_i18n_presets.md":"D05zyWhg","de-de_guide_i18n_translation.md":"CRcGuZ7H","de-de_guide_index.md":"BxSyUxYI","de-de_guide_plugin_filter.md":"Dvl1GuoD","de-de_guide_plugin_index.md":"BlPYgHSb","de-de_guide_plugin_lifecycle.md":"B1ARtIS_","de-de_guide_plugin_schema.md":"CMKbuoBF","de-de_guide_plugin_selector.md":"WPjd4Rcw","de-de_guide_plugin_service.md":"S_Ua995N","de-de_index.md":"NQsMBE3P","de-de_manual_faq.md":"CRYvjH_Q","de-de_manual_introduction.md":"Dx4FERnd","de-de_manual_launcher_cli.md":"BkmjznUQ","de-de_manual_launcher_system.md":"CKG6z14D","de-de_manual_recipe_dataview.md":"Df1lxCEx","de-de_manual_recipe_execution.md":"DhViToRe","de-de_manual_recipe_multiple.md":"B2S1ljyt","de-de_manual_recipe_search.md":"bXA4R-2A","de-de_manual_recipe_server.md":"BE6vFkGT","de-de_manual_starter_android.md":"BcQEB7ZK","de-de_manual_starter_boilerplate.md":"vYInH92v","de-de_manual_starter_direct.md":"B7LhzLZA","de-de_manual_starter_docker.md":"IIbBbb9e","de-de_manual_starter_index.md":"CLVgfACt","de-de_manual_starter_linux.md":"CxJ6O9y8","de-de_manual_starter_macos.md":"BCqzWsrp","de-de_manual_starter_windows.md":"Dr4Fge1V","de-de_manual_usage_adapter.md":"9ZKcNmjv","de-de_manual_usage_command.md":"CkNcyblQ","de-de_manual_usage_customize.md":"CCZgGFGq","de-de_manual_usage_market.md":"CBo8p-yj","de-de_manual_usage_platform.md":"xvm3eij8","de-de_market_index.md":"CopkV0G8","de-de_market_service.md":"Q70NdNF4","de-de_plugins_adapter_dingtalk.md":"xrXS0d6u","de-de_plugins_adapter_discord.md":"DKD1lnZy","de-de_plugins_adapter_kook.md":"qSc9T7rO","de-de_plugins_adapter_lark.md":"C6tHiOMe","de-de_plugins_adapter_line.md":"CpiCizAt","de-de_plugins_adapter_mail.md":"C7PenvMU","de-de_plugins_adapter_matrix.md":"D7GiK0qg","de-de_plugins_adapter_onebot.md":"DVZWsrub","de-de_plugins_adapter_qq.md":"CXSO4Whq","de-de_plugins_adapter_qqguild.md":"B2dweBlg","de-de_plugins_adapter_satori.md":"CKfnBrL3","de-de_plugins_adapter_slack.md":"CHEtfWI0","de-de_plugins_adapter_telegram.md":"BV_nHe-m","de-de_plugins_adapter_wechat-official.md":"DJxlSHPv","de-de_plugins_adapter_wecom.md":"wcNVYnmU","de-de_plugins_adapter_whatsapp.md":"4I4pXw6_","de-de_plugins_adapter_zulip.md":"BJZSKcVQ","de-de_plugins_common_admin.md":"XQjT82gL","de-de_plugins_common_bind.md":"B6cO6Fkd","de-de_plugins_common_broadcast.md":"cdPraMnU","de-de_plugins_common_callme.md":"COw8SHfO","de-de_plugins_common_echo.md":"CAs7rQvA","de-de_plugins_common_help.md":"CHXpqAwp","de-de_plugins_common_inspect.md":"CSCB1B4J","de-de_plugins_common_rate-limit.md":"C5gnQ2gB","de-de_plugins_console_analytics.md":"Ccyritxl","de-de_plugins_console_auth.md":"BOGQiwCv","de-de_plugins_console_commands.md":"qarXDuDj","de-de_plugins_console_config.md":"Do7WvYAG","de-de_plugins_console_dataview.md":"zDQZXYDq","de-de_plugins_console_explorer.md":"wU8Zd2cc","de-de_plugins_console_index.md":"ByuDANt6","de-de_plugins_console_insight.md":"CW-wjWhn","de-de_plugins_console_locales.md":"Cr1j-XGB","de-de_plugins_console_logger.md":"DU3Bgf1e","de-de_plugins_console_login.md":"RtipTAHt","de-de_plugins_console_market.md":"CdnD8Zt-","de-de_plugins_console_sandbox.md":"BkUN93b_","de-de_plugins_console_status.md":"ChKRLlIw","de-de_plugins_database_memory.md":"BolyITb3","de-de_plugins_database_mongo.md":"DwNhU6qN","de-de_plugins_database_mysql.md":"JWnW3BD0","de-de_plugins_database_postgres.md":"BYTY42Pv","de-de_plugins_database_sqlite.md":"zByXSafi","de-de_plugins_develop_hmr.md":"DbSb3l22","de-de_plugins_develop_mock.md":"D1QdVCsY","de-de_plugins_develop_server-proxy.md":"f7pSK2IR","de-de_plugins_develop_server-satori.md":"DDmIi0cy","de-de_plugins_develop_server-temp.md":"CMwWT7DE","de-de_plugins_develop_server.md":"D1e69E_Z","de-de_plugins_index.md":"DBCHAXaO","de-de_releases_index.md":"CbX3wkRD","de-de_releases_v4.1.md":"IjkbjD5n","de-de_releases_v4.10.md":"C1MCLHc4","de-de_releases_v4.11.md":"DQVRjtMj","de-de_releases_v4.12.md":"CccO-iNW","de-de_releases_v4.13.md":"LINtqL80","de-de_releases_v4.14.md":"DFO7ew4s","de-de_releases_v4.15.md":"DARHXmYz","de-de_releases_v4.2.md":"CyKQhV_q","de-de_releases_v4.3.md":"Dcau3Ad1","de-de_releases_v4.4.md":"BEsxOckg","de-de_releases_v4.5.md":"BHHEfS13","de-de_releases_v4.6.md":"j-Q8AlA1","de-de_releases_v4.7.md":"VtpixrXK","de-de_releases_v4.8.md":"-S7jfXoF","de-de_releases_v4.9.md":"B6BCXO82","de-de_schema_advanced_computed.md":"oz9IqwHw","de-de_schema_advanced_dynamic.md":"Drsb5uOS","de-de_schema_advanced_intersect.md":"BOxkwx1F","de-de_schema_advanced_transform.md":"CkUAieGH","de-de_schema_advanced_union-arbitrary.md":"CcfQnFJi","de-de_schema_advanced_union-select.md":"DYJVqYAR","de-de_schema_advanced_union-tagged-1.md":"j6jVpPRH","de-de_schema_advanced_union-tagged-2.md":"CJvfbDEy","de-de_schema_basic_array.md":"B-a6gtyM","de-de_schema_basic_bitset.md":"DGHZMJ9g","de-de_schema_basic_boolean.md":"rpDsOlST","de-de_schema_basic_date.md":"CiBKQLvf","de-de_schema_basic_dict.md":"NCqie9kN","de-de_schema_basic_number.md":"jlrJWfKi","de-de_schema_basic_object.md":"D_uhgTt0","de-de_schema_basic_path.md":"BNBvmvoW","de-de_schema_basic_string.md":"CtyIyF9h","de-de_schema_basic_tuple.md":"BVBSNM1U","de-de_schema_index.md":"Be7DKJz4","de-de_schema_meta_default.md":"Cw9lkVM1","de-de_schema_meta_description.md":"DpUt-drY","de-de_schema_meta_disabled.md":"Dv4ELkz5","de-de_schema_meta_hidden.md":"z-0pHNew","de-de_schema_meta_nested.md":"CH8f7XCW","de-de_schema_meta_required.md":"CguXc-wS","de-de_schema_meta_role.md":"BosVufw3","en-us_about_community.md":"DlHyJt8k","en-us_about_contact.md":"BzlVVJ5x","en-us_about_contribute_docs.md":"9gYCbjpS","en-us_about_contribute_structure.md":"CWaNp8r5","en-us_about_events.md":"CYJk1FR6","en-us_about_faq.md":"fLA0xjk-","en-us_about_history.md":"C7y2MBGQ","en-us_about_license.md":"BKs7Sskx","en-us_about_migration.md":"gYxMEiak","en-us_about_releases.md":"zSBSeA1z","en-us_about_releases_v4.1.md":"DBdBmCTi","en-us_about_releases_v4.10.md":"BvcNfR4a","en-us_about_releases_v4.11.md":"D5WAB7dW","en-us_about_releases_v4.12.md":"D8zqAQ0M","en-us_about_releases_v4.13.md":"cASgYIie","en-us_about_releases_v4.14.md":"BGXdXCJC","en-us_about_releases_v4.15.md":"B8gG8rnz","en-us_about_releases_v4.2.md":"cxnZUFqB","en-us_about_releases_v4.3.md":"BkxldW0S","en-us_about_releases_v4.4.md":"CvpjeCIn","en-us_about_releases_v4.5.md":"DDRSViR5","en-us_about_releases_v4.6.md":"CPu2iBxq","en-us_about_releases_v4.7.md":"C1tsfUAK","en-us_about_releases_v4.8.md":"CjZkZrsi","en-us_about_releases_v4.9.md":"DkYyldtV","en-us_about_team.md":"QfSzhNzP","en-us_about_upgrade.md":"D17R1HHi","en-us_api_console_component.md":"C0VbE9Y1","en-us_api_console_composition.md":"Df3-DNKs","en-us_api_console_context.md":"zTY4Nwec","en-us_api_console_server.md":"BOUbpMmq","en-us_api_core_adapter.md":"C4fW1W5F","en-us_api_core_app.md":"BoptMKWy","en-us_api_core_bot.md":"CUEIjBBZ","en-us_api_core_command.md":"CIVRlbfq","en-us_api_core_context.md":"DBHVUMdN","en-us_api_core_events.md":"C0wyTvbg","en-us_api_core_session.md":"C4wDf27m","en-us_api_database_built-in.md":"BtTQauM5","en-us_api_database_database.md":"BmXq2vgc","en-us_api_database_evaluation.md":"CdXK4dVb","en-us_api_database_model.md":"DTKrNOB4","en-us_api_database_query.md":"F8krr9mT","en-us_api_database_selection.md":"DtjbwQxZ","en-us_api_glossary.md":"EUbjHfto","en-us_api_index.md":"BWNUvVbe","en-us_api_message_api.md":"C1zsNiKa","en-us_api_message_components.md":"Bz1_YQZt","en-us_api_message_elements.md":"bFgFOw3x","en-us_api_message_encoder.md":"CAdhpXWE","en-us_api_message_syntax.md":"VLHbjQai","en-us_api_platform_channel.md":"DkhkLcCl","en-us_api_platform_guild.md":"C3kYED6-","en-us_api_platform_member.md":"DTS8ViF1","en-us_api_platform_message.md":"DhU3mpSM","en-us_api_platform_reaction.md":"DASPdYX8","en-us_api_platform_role.md":"Cw7_22sR","en-us_api_platform_user.md":"AfniTNpi","en-us_api_resources_channel.md":"CXLoTImL","en-us_api_resources_guild.md":"ajz1XRDq","en-us_api_resources_interaction.md":"CqPiPUx-","en-us_api_resources_login.md":"ZjbFhKo9","en-us_api_resources_member.md":"CWsxEgCy","en-us_api_resources_message.md":"DI3NEfgb","en-us_api_resources_reaction.md":"4B8JxqhL","en-us_api_resources_role.md":"jbHh6Z3y","en-us_api_resources_user.md":"5o3M4D1F","en-us_api_service_bots.md":"CZUjBNbj","en-us_api_service_events.md":"d7L4MW4-","en-us_api_service_filter.md":"BLEuP8PP","en-us_api_service_http.md":"C0arMGn7","en-us_api_service_i18n.md":"I8qnGrFN","en-us_api_service_lifecycle.md":"CEeAOSzu","en-us_api_service_loader.md":"VmnzoXc2","en-us_api_service_logger.md":"C-wRjNfv","en-us_api_service_permissions.md":"BBUnvp0b","en-us_api_service_registry.md":"D1hH81SL","en-us_api_service_router.md":"D7fSG2NE","en-us_api_service_selector.md":"DSikoFwn","en-us_api_utils_logger.md":"BBpVJAH6","en-us_api_utils_misc.md":"Ci212Igu","en-us_api_utils_observer.md":"DPaplF-M","en-us_api_utils_random.md":"BYCyyU0d","en-us_api_utils_schema.md":"BpYcPlW7","en-us_cookbook_appendix_commands.md":"BRY7TJE8","en-us_cookbook_assets.md":"DHMeHPDc","en-us_cookbook_design_bundle.md":"BOpsDpk5","en-us_cookbook_design_disposable.md":"ynoAw-Ke","en-us_cookbook_design_framework.md":"DNpIw1Pp","en-us_cookbook_design_reversible.md":"D1ZLOsqh","en-us_cookbook_design_storage.md":"D6fC2zmD","en-us_cookbook_design_structure.md":"BGd76nX_","en-us_cookbook_design_workspace.md":"BjU0gH1A","en-us_cookbook_index.md":"B_Nh6bvN","en-us_cookbook_message.md":"BAD8kWla","en-us_cookbook_online.md":"BUBysE5-","en-us_cookbook_practice_assets.md":"CW4_D8Q4","en-us_cookbook_practice_bundle.md":"D79l0qA_","en-us_cookbook_practice_online.md":"grgrgB7m","en-us_cookbook_practice_render.md":"BM2K5R_Z","en-us_cookbook_practice_testing.md":"D_5Ft_0k","en-us_cookbook_render.md":"C2BEre1D","en-us_cookbook_storage.md":"Bq0YR3mh","en-us_cookbook_testing.md":"D22RoDva","en-us_guide_adapter_adapter.md":"Vb30tMLE","en-us_guide_adapter_bot.md":"DtQABxkO","en-us_guide_adapter_index.md":"2F_bCSP4","en-us_guide_adapter_integration.md":"D4J8CCbu","en-us_guide_adapter_message.md":"AqzAz9zw","en-us_guide_basic_advanced.md":"dFVRqv-d","en-us_guide_basic_command.md":"CkO1df89","en-us_guide_basic_element.md":"CWDoQR4I","en-us_guide_basic_events.md":"CEl8hjgr","en-us_guide_basic_middleware.md":"CMK2vDVK","en-us_guide_console_client.md":"Ccy9q0DH","en-us_guide_console_data.md":"VIfkDphP","en-us_guide_console_index.md":"Cs19qy9x","en-us_guide_console_theme.md":"CKXjt-IW","en-us_guide_database_builtin.md":"B0FN55no","en-us_guide_database_index.md":"BuXgZBgW","en-us_guide_database_model.md":"C5cBf8PB","en-us_guide_database_observer.md":"D3bEFugo","en-us_guide_database_permission.md":"Ld9MEtXX","en-us_guide_database_select.md":"B4dD5nhS","en-us_guide_database_selection.md":"BMhGhhmj","en-us_guide_database_writing.md":"jD2eIdIC","en-us_guide_develop_config.md":"CM9cjv5u","en-us_guide_develop_publish.md":"CBBw_mF_","en-us_guide_develop_script.md":"Br7bpylf","en-us_guide_develop_setup.md":"BiRXJ6sL","en-us_guide_develop_workspace.md":"Dh7TmB8E","en-us_guide_i18n_crowdin.md":"BjeDCZOS","en-us_guide_i18n_index.md":"DJoCdCzJ","en-us_guide_i18n_lang-pack.md":"DTrGsXiX","en-us_guide_i18n_presets.md":"Djtr5YyT","en-us_guide_i18n_translation.md":"D3-7gS0d","en-us_guide_index.md":"KnzH2mix","en-us_guide_plugin_filter.md":"C0bzWw5S","en-us_guide_plugin_index.md":"BPmIfDZk","en-us_guide_plugin_lifecycle.md":"BHcNxTUF","en-us_guide_plugin_schema.md":"BQ_Jq_JN","en-us_guide_plugin_service.md":"B-lOFULs","en-us_index.md":"CwMDd7MQ","en-us_manual_faq.md":"CEx9XbB6","en-us_manual_introduction.md":"ep_IlZUY","en-us_manual_launcher_cli.md":"DHKphLnb","en-us_manual_launcher_system.md":"Bzms4Gvf","en-us_manual_recipe_dataview.md":"LT-4gmef","en-us_manual_recipe_execution.md":"H7IYhLZg","en-us_manual_recipe_multiple.md":"B7g8hLC8","en-us_manual_recipe_search.md":"DuSavSiq","en-us_manual_recipe_server.md":"B3Eciwze","en-us_manual_starter_android.md":"B1GGwQHA","en-us_manual_starter_boilerplate.md":"CZwpAewv","en-us_manual_starter_direct.md":"BrceUQQS","en-us_manual_starter_docker.md":"elzLAzfW","en-us_manual_starter_index.md":"H5XOARXE","en-us_manual_starter_linux.md":"CkuZFOJD","en-us_manual_starter_macos.md":"C4-aOsVE","en-us_manual_starter_windows.md":"DwoAHXD_","en-us_manual_usage_adapter.md":"CFyvcyDw","en-us_manual_usage_command.md":"B9ka_Na8","en-us_manual_usage_customize.md":"DrOXMM5m","en-us_manual_usage_market.md":"CIf05s2u","en-us_manual_usage_platform.md":"AumQOzpQ","en-us_market_index.md":"sXAUVHuk","en-us_market_service.md":"BzMaN8Iw","en-us_plugins_adapter_dingtalk.md":"DPyqqLSp","en-us_plugins_adapter_discord.md":"CHKx9xGL","en-us_plugins_adapter_kook.md":"D9N6Clpk","en-us_plugins_adapter_lark.md":"idC2NPEL","en-us_plugins_adapter_line.md":"CquTXno1","en-us_plugins_adapter_mail.md":"vHB1YHpt","en-us_plugins_adapter_matrix.md":"C7RZMP9C","en-us_plugins_adapter_onebot.md":"oEDOBz8Y","en-us_plugins_adapter_qq.md":"B-E2rqKp","en-us_plugins_adapter_qqguild.md":"Dpr7ciQT","en-us_plugins_adapter_satori.md":"DBgXz1KL","en-us_plugins_adapter_slack.md":"BD5h6zYU","en-us_plugins_adapter_telegram.md":"DeoxROqD","en-us_plugins_adapter_wechat-official.md":"CgjnAOp3","en-us_plugins_adapter_wecom.md":"CcXz0GvF","en-us_plugins_adapter_whatsapp.md":"lIxbILLK","en-us_plugins_adapter_zulip.md":"HAYXUeQJ","en-us_plugins_common_admin.md":"CVTM_QZj","en-us_plugins_common_bind.md":"1puxImVs","en-us_plugins_common_broadcast.md":"DdHGO8qt","en-us_plugins_common_callme.md":"BySKYd_R","en-us_plugins_common_echo.md":"BGXQcFwA","en-us_plugins_common_help.md":"BZ4U50At","en-us_plugins_common_inspect.md":"xFxx0wZ0","en-us_plugins_common_rate-limit.md":"U5dhfl6g","en-us_plugins_console_analytics.md":"C71X68fE","en-us_plugins_console_auth.md":"jTLwshcs","en-us_plugins_console_commands.md":"BEsOCBzc","en-us_plugins_console_config.md":"D4MkyMBW","en-us_plugins_console_dataview.md":"L0sHI6F9","en-us_plugins_console_explorer.md":"BLTfJ6T0","en-us_plugins_console_index.md":"DHxhy15n","en-us_plugins_console_insight.md":"BlUYcxr_","en-us_plugins_console_locales.md":"6wKyBbZ5","en-us_plugins_console_logger.md":"CKG8-GMz","en-us_plugins_console_login.md":"WGK4K4YH","en-us_plugins_console_market.md":"CQcjeMEC","en-us_plugins_console_sandbox.md":"C5SlevXJ","en-us_plugins_console_status.md":"CFT34KeE","en-us_plugins_database_memory.md":"CbqPjteM","en-us_plugins_database_mongo.md":"B5bhzpZX","en-us_plugins_database_mysql.md":"BDKJo7TA","en-us_plugins_database_postgres.md":"nddl8gl1","en-us_plugins_database_sqlite.md":"sXkUanmg","en-us_plugins_develop_hmr.md":"D5qf7hmG","en-us_plugins_develop_mock.md":"m_rScLKI","en-us_plugins_develop_server-proxy.md":"CWIPNNL9","en-us_plugins_develop_server-satori.md":"Qo3Lpc21","en-us_plugins_develop_server-temp.md":"C-VxdUmn","en-us_plugins_develop_server.md":"Bhx8nJHY","en-us_plugins_index.md":"BrtE9i8P","en-us_releases_index.md":"C6mJHZDM","en-us_releases_v4.1.md":"DRiXz7mA","en-us_releases_v4.10.md":"krdHj89v","en-us_releases_v4.11.md":"CzB7KVUE","en-us_releases_v4.12.md":"Bz3ffb52","en-us_releases_v4.13.md":"K76zfJLE","en-us_releases_v4.14.md":"CmndvCr3","en-us_releases_v4.15.md":"BSguZNPN","en-us_releases_v4.2.md":"D0V2DJjI","en-us_releases_v4.3.md":"DMlcHf2e","en-us_releases_v4.4.md":"D6OqkEHJ","en-us_releases_v4.5.md":"BmWcv7ar","en-us_releases_v4.6.md":"se4ADxov","en-us_releases_v4.7.md":"tQBPp1ao","en-us_releases_v4.8.md":"Corz2J8I","en-us_releases_v4.9.md":"DAWJPJFJ","en-us_schema_advanced_computed.md":"CmhVJQfi","en-us_schema_advanced_dynamic.md":"ZjdwHiHZ","en-us_schema_advanced_intersect.md":"_Bz3bv-2","en-us_schema_advanced_transform.md":"Chi41tTy","en-us_schema_advanced_union-arbitrary.md":"BUZghMQY","en-us_schema_advanced_union-select.md":"JjYW7Oms","en-us_schema_advanced_union-tagged-1.md":"DUoyhYq-","en-us_schema_advanced_union-tagged-2.md":"KYlEh_ck","en-us_schema_basic_array.md":"BEs_ZgBx","en-us_schema_basic_bitset.md":"DKtMQcAj","en-us_schema_basic_boolean.md":"BFXV4MJI","en-us_schema_basic_date.md":"Jyn01wU7","en-us_schema_basic_dict.md":"C1p-97Lz","en-us_schema_basic_number.md":"DnheRYq3","en-us_schema_basic_object.md":"kCU0IHUo","en-us_schema_basic_path.md":"Buv6Er8z","en-us_schema_basic_string.md":"CtdKZ2vZ","en-us_schema_basic_tuple.md":"BuNJJ2z8","en-us_schema_index.md":"6cgSz5uQ","en-us_schema_meta_default.md":"SKrdFoAa","en-us_schema_meta_description.md":"DBrwFeel","en-us_schema_meta_disabled.md":"D_T1OKAj","en-us_schema_meta_hidden.md":"D363A2IQ","en-us_schema_meta_nested.md":"B4CfoX9a","en-us_schema_meta_required.md":"Dc05nfnL","en-us_schema_meta_role.md":"DpZIJvID","fr-fr_about_community.md":"D86OUgNJ","fr-fr_about_contact.md":"BnApaO2F","fr-fr_about_contribute_docs.md":"BqXBOFm-","fr-fr_about_contribute_structure.md":"cn-X3ktL","fr-fr_about_events.md":"Bmz23U5U","fr-fr_about_faq.md":"DAN-OAyu","fr-fr_about_history.md":"Doq6MXYq","fr-fr_about_license.md":"BWRlJn-X","fr-fr_about_migration.md":"CrlJxr2R","fr-fr_about_releases.md":"IQTBmKIa","fr-fr_about_releases_v4.1.md":"lcmcZv_t","fr-fr_about_releases_v4.10.md":"CjIAli22","fr-fr_about_releases_v4.11.md":"B41emkLe","fr-fr_about_releases_v4.12.md":"Bujb67d9","fr-fr_about_releases_v4.13.md":"Lr_TmR-f","fr-fr_about_releases_v4.14.md":"DlhZjxsl","fr-fr_about_releases_v4.15.md":"zpuicun_","fr-fr_about_releases_v4.2.md":"eEKO-Q6m","fr-fr_about_releases_v4.3.md":"Bq2crYmd","fr-fr_about_releases_v4.4.md":"CfbGcrMg","fr-fr_about_releases_v4.5.md":"tYOZkdkd","fr-fr_about_releases_v4.6.md":"BaTGFh3V","fr-fr_about_releases_v4.7.md":"DrTuSqsa","fr-fr_about_releases_v4.8.md":"V1MURJaQ","fr-fr_about_releases_v4.9.md":"CP_eWuP4","fr-fr_about_team.md":"CdP6_WR3","fr-fr_about_upgrade.md":"Hp2vg3fM","fr-fr_api_console_component.md":"Dvya3P09","fr-fr_api_console_composition.md":"AROnapib","fr-fr_api_console_context.md":"CoUUTo_Z","fr-fr_api_console_server.md":"BmZtMAGg","fr-fr_api_core_adapter.md":"C0H-yGqI","fr-fr_api_core_app.md":"CVcIpE91","fr-fr_api_core_bot.md":"Q3l7qYqE","fr-fr_api_core_command.md":"CYDNdAzy","fr-fr_api_core_context.md":"DZ0u6yyA","fr-fr_api_core_events.md":"BC6W6Tdy","fr-fr_api_core_session.md":"BpcnnQE9","fr-fr_api_database_built-in.md":"CW5lTBYc","fr-fr_api_database_database.md":"DCkLVnYx","fr-fr_api_database_evaluation.md":"CFoxRvMt","fr-fr_api_database_model.md":"6XYP2GpD","fr-fr_api_database_query.md":"ClAuQEk0","fr-fr_api_database_selection.md":"CTcG_4wo","fr-fr_api_glossary.md":"DL43S58Y","fr-fr_api_index.md":"DS527jaA","fr-fr_api_message_api.md":"DFgdfL52","fr-fr_api_message_components.md":"BMri3wti","fr-fr_api_message_elements.md":"C8cNg8ta","fr-fr_api_message_encoder.md":"DRT_oDhJ","fr-fr_api_message_syntax.md":"Dfhw1Bkn","fr-fr_api_platform_channel.md":"BWW0GB-B","fr-fr_api_platform_guild.md":"Dfmd5asU","fr-fr_api_platform_member.md":"CwaOwR8E","fr-fr_api_platform_message.md":"k6cstOYG","fr-fr_api_platform_reaction.md":"B0TwvqNU","fr-fr_api_platform_role.md":"2IPn0xUO","fr-fr_api_platform_user.md":"DITq8nOv","fr-fr_api_resources_channel.md":"GKuAL3p-","fr-fr_api_resources_guild.md":"CeXSgTRD","fr-fr_api_resources_interaction.md":"CpJE4VQX","fr-fr_api_resources_login.md":"XmIK-_EX","fr-fr_api_resources_member.md":"Zp5MftQw","fr-fr_api_resources_message.md":"DdN-j90w","fr-fr_api_resources_reaction.md":"CQICbs2S","fr-fr_api_resources_role.md":"DKX75rod","fr-fr_api_resources_user.md":"Ba4oH7ys","fr-fr_api_service_bots.md":"BKalfoHD","fr-fr_api_service_events.md":"CYPIO1pH","fr-fr_api_service_filter.md":"4-vKKPSm","fr-fr_api_service_http.md":"BYhCik9_","fr-fr_api_service_i18n.md":"B264jbsp","fr-fr_api_service_lifecycle.md":"DZAbeMXz","fr-fr_api_service_loader.md":"gng68wTx","fr-fr_api_service_logger.md":"9tX3F2D7","fr-fr_api_service_permissions.md":"bw_tRmJC","fr-fr_api_service_registry.md":"DIAflSEJ","fr-fr_api_service_router.md":"CM-1KKFc","fr-fr_api_service_selector.md":"BMIDvnNq","fr-fr_api_utils_logger.md":"DEPA660c","fr-fr_api_utils_misc.md":"DYXe2gwW","fr-fr_api_utils_observer.md":"SXhm6AOE","fr-fr_api_utils_random.md":"BCZzJHyu","fr-fr_api_utils_schema.md":"BeDUMTWV","fr-fr_cookbook_appendix_commands.md":"DZFqnQID","fr-fr_cookbook_assets.md":"DlMj2tG6","fr-fr_cookbook_design_bundle.md":"Awg9SuCp","fr-fr_cookbook_design_disposable.md":"DX_YNG2a","fr-fr_cookbook_design_framework.md":"BeLPDkss","fr-fr_cookbook_design_reversible.md":"CmastkVG","fr-fr_cookbook_design_storage.md":"DyBjpFfr","fr-fr_cookbook_design_structure.md":"C8mClLhG","fr-fr_cookbook_design_workspace.md":"fC1O48me","fr-fr_cookbook_index.md":"CHd5HTW2","fr-fr_cookbook_message.md":"CJ-PHwuR","fr-fr_cookbook_online.md":"DbF1aLbk","fr-fr_cookbook_practice_assets.md":"Ca44SD9V","fr-fr_cookbook_practice_bundle.md":"CL2OVwba","fr-fr_cookbook_practice_online.md":"DKOesWiD","fr-fr_cookbook_practice_render.md":"B7KT0lsB","fr-fr_cookbook_practice_testing.md":"C00dvRAR","fr-fr_cookbook_render.md":"BShQDT_P","fr-fr_cookbook_storage.md":"Dvavgjzp","fr-fr_cookbook_testing.md":"CmH0laPa","fr-fr_guide_adapter_adapter.md":"C4qcEiOO","fr-fr_guide_adapter_bot.md":"0LQwri2_","fr-fr_guide_adapter_index.md":"BNGl2JeO","fr-fr_guide_adapter_integration.md":"DyIgFkXe","fr-fr_guide_adapter_message.md":"5UrpsYYx","fr-fr_guide_basic_advanced.md":"DB2q-dPU","fr-fr_guide_basic_command.md":"CK308rqe","fr-fr_guide_basic_element.md":"BOedJrfa","fr-fr_guide_basic_events.md":"fiPUfj_U","fr-fr_guide_basic_middleware.md":"BRugAbJ_","fr-fr_guide_console_client.md":"Dr_n9pk6","fr-fr_guide_console_data.md":"D9ZYatyY","fr-fr_guide_console_index.md":"Bv-eOj5A","fr-fr_guide_console_theme.md":"kJ8uzFpp","fr-fr_guide_database_builtin.md":"C4OFz7-T","fr-fr_guide_database_index.md":"d_gry4Ja","fr-fr_guide_database_model.md":"CUa7gQHw","fr-fr_guide_database_observer.md":"Df_AYBDy","fr-fr_guide_database_permission.md":"BK_zpswt","fr-fr_guide_database_select.md":"CzMz8G8B","fr-fr_guide_database_selection.md":"BFbC8_i5","fr-fr_guide_database_writing.md":"D7HSL36t","fr-fr_guide_develop_config.md":"BIpU7T97","fr-fr_guide_develop_publish.md":"BXXLJikp","fr-fr_guide_develop_script.md":"CP0h9gka","fr-fr_guide_develop_setup.md":"Cd0HpEhT","fr-fr_guide_develop_workspace.md":"p46U9e7X","fr-fr_guide_i18n_crowdin.md":"CtOARG8y","fr-fr_guide_i18n_index.md":"DWrPSKS2","fr-fr_guide_i18n_lang-pack.md":"361V1vhI","fr-fr_guide_i18n_presets.md":"BZ_VTb3g","fr-fr_guide_i18n_translation.md":"DoeLF8C0","fr-fr_guide_index.md":"CPnLVO1x","fr-fr_guide_plugin_filter.md":"C8OYzS73","fr-fr_guide_plugin_index.md":"ExGVobsY","fr-fr_guide_plugin_lifecycle.md":"CBJ_KRWu","fr-fr_guide_plugin_schema.md":"C8rspm1O","fr-fr_guide_plugin_selector.md":"D7fu44AW","fr-fr_guide_plugin_service.md":"D1EGO4ZN","fr-fr_index.md":"Bar24MpL","fr-fr_manual_faq.md":"CCGCj19j","fr-fr_manual_introduction.md":"C3brmX2a","fr-fr_manual_launcher_cli.md":"DUQDj-Yp","fr-fr_manual_launcher_system.md":"4dDhIWTy","fr-fr_manual_recipe_dataview.md":"DPFvV4BH","fr-fr_manual_recipe_execution.md":"DvaTkx1D","fr-fr_manual_recipe_multiple.md":"COX7LPvc","fr-fr_manual_recipe_search.md":"jXuWH_LM","fr-fr_manual_recipe_server.md":"-ChQ4bDv","fr-fr_manual_starter_android.md":"C5n8YpuH","fr-fr_manual_starter_boilerplate.md":"C2u4WQ0V","fr-fr_manual_starter_direct.md":"BWIcwhPZ","fr-fr_manual_starter_docker.md":"BCQO1rmA","fr-fr_manual_starter_index.md":"BsuMUhxZ","fr-fr_manual_starter_linux.md":"pUxIxcKm","fr-fr_manual_starter_macos.md":"C4UmQJEL","fr-fr_manual_starter_windows.md":"BlXnwimW","fr-fr_manual_usage_adapter.md":"tJ61ms2W","fr-fr_manual_usage_command.md":"C5HebO57","fr-fr_manual_usage_customize.md":"CeCag-c7","fr-fr_manual_usage_market.md":"ClBQHJPo","fr-fr_manual_usage_platform.md":"C9eNaxyo","fr-fr_market_index.md":"Db7oLhKt","fr-fr_market_service.md":"CS0bIvRi","fr-fr_plugins_adapter_dingtalk.md":"DuuILV8d","fr-fr_plugins_adapter_discord.md":"DBfB0zUT","fr-fr_plugins_adapter_kook.md":"DuA4jK_x","fr-fr_plugins_adapter_lark.md":"DjczyUxI","fr-fr_plugins_adapter_line.md":"BXNJLmjt","fr-fr_plugins_adapter_mail.md":"D_nBn7_U","fr-fr_plugins_adapter_matrix.md":"DNyiifVw","fr-fr_plugins_adapter_onebot.md":"CPz--puO","fr-fr_plugins_adapter_qq.md":"Bl9pwIAY","fr-fr_plugins_adapter_qqguild.md":"BuFfdk95","fr-fr_plugins_adapter_satori.md":"CJEDtNBS","fr-fr_plugins_adapter_slack.md":"BT7EjYIQ","fr-fr_plugins_adapter_telegram.md":"CRwWYw2h","fr-fr_plugins_adapter_wechat-official.md":"DB53bpxn","fr-fr_plugins_adapter_wecom.md":"dZahYgIG","fr-fr_plugins_adapter_whatsapp.md":"BX0NkAhM","fr-fr_plugins_adapter_zulip.md":"BPMSreL3","fr-fr_plugins_common_admin.md":"DyR_RGqb","fr-fr_plugins_common_bind.md":"zOey3yWk","fr-fr_plugins_common_broadcast.md":"BV8XwbY9","fr-fr_plugins_common_callme.md":"DF-MbaKm","fr-fr_plugins_common_echo.md":"CDcJide_","fr-fr_plugins_common_help.md":"DN0cVWhX","fr-fr_plugins_common_inspect.md":"B-adoAZQ","fr-fr_plugins_common_rate-limit.md":"BeLLQyeY","fr-fr_plugins_console_analytics.md":"lp2GDIG8","fr-fr_plugins_console_auth.md":"CxgcTL8s","fr-fr_plugins_console_commands.md":"DZ5g3ums","fr-fr_plugins_console_config.md":"DJAbp7je","fr-fr_plugins_console_dataview.md":"BUyM93gp","fr-fr_plugins_console_explorer.md":"KlytvKtX","fr-fr_plugins_console_index.md":"DYMGxWMN","fr-fr_plugins_console_insight.md":"Bu4bzNm0","fr-fr_plugins_console_locales.md":"Y6ZNrSvG","fr-fr_plugins_console_logger.md":"C9xHgTXz","fr-fr_plugins_console_login.md":"BdmJ0mHE","fr-fr_plugins_console_market.md":"CRxQ-paH","fr-fr_plugins_console_sandbox.md":"ChhgIA-H","fr-fr_plugins_console_status.md":"Dy1fUEjr","fr-fr_plugins_database_memory.md":"Be1o6PhU","fr-fr_plugins_database_mongo.md":"CfpSrU8j","fr-fr_plugins_database_mysql.md":"C03A71Sa","fr-fr_plugins_database_postgres.md":"ilyaT6Bc","fr-fr_plugins_database_sqlite.md":"C_fyIikW","fr-fr_plugins_develop_hmr.md":"C29dnH9D","fr-fr_plugins_develop_mock.md":"ByqXuOT9","fr-fr_plugins_develop_server-proxy.md":"DX1LAJq7","fr-fr_plugins_develop_server-satori.md":"C0I6l2P5","fr-fr_plugins_develop_server-temp.md":"CGcm4sFd","fr-fr_plugins_develop_server.md":"D7KBVqQN","fr-fr_plugins_index.md":"BqI_Frwv","fr-fr_releases_index.md":"CpZXiU9D","fr-fr_releases_v4.1.md":"BNwzB5j6","fr-fr_releases_v4.10.md":"tJeOE3mq","fr-fr_releases_v4.11.md":"DsELzkti","fr-fr_releases_v4.12.md":"BQ9O0iYZ","fr-fr_releases_v4.13.md":"CiCWaZBJ","fr-fr_releases_v4.14.md":"CyrX8NXy","fr-fr_releases_v4.15.md":"DPvvmGkT","fr-fr_releases_v4.2.md":"ZFZkRHhT","fr-fr_releases_v4.3.md":"C_gBEPfL","fr-fr_releases_v4.4.md":"JCDtFaKl","fr-fr_releases_v4.5.md":"CWuPBLoX","fr-fr_releases_v4.6.md":"B7yIbE8n","fr-fr_releases_v4.7.md":"BGjmyRYK","fr-fr_releases_v4.8.md":"CBTf9rIm","fr-fr_releases_v4.9.md":"CWe-XLzR","fr-fr_schema_advanced_computed.md":"CkmbgqNN","fr-fr_schema_advanced_dynamic.md":"gW9ZLZ2Z","fr-fr_schema_advanced_intersect.md":"D5RReHC3","fr-fr_schema_advanced_transform.md":"BcCaZXdI","fr-fr_schema_advanced_union-arbitrary.md":"B95NY0z4","fr-fr_schema_advanced_union-select.md":"CyhYdzUq","fr-fr_schema_advanced_union-tagged-1.md":"DNirIwhL","fr-fr_schema_advanced_union-tagged-2.md":"kfcuboQ8","fr-fr_schema_basic_array.md":"Cby1td_D","fr-fr_schema_basic_bitset.md":"C-yLgbAr","fr-fr_schema_basic_boolean.md":"A5Ck4AY7","fr-fr_schema_basic_date.md":"BRy7SeX0","fr-fr_schema_basic_dict.md":"Cx1l5UII","fr-fr_schema_basic_number.md":"C5HdS1fp","fr-fr_schema_basic_object.md":"CziJzL9W","fr-fr_schema_basic_path.md":"D8Tz1ecN","fr-fr_schema_basic_string.md":"Bw3H8FWF","fr-fr_schema_basic_tuple.md":"Ch5C20_G","fr-fr_schema_index.md":"gcyZNxFz","fr-fr_schema_meta_default.md":"B3mVdeqz","fr-fr_schema_meta_description.md":"iCQyzfkU","fr-fr_schema_meta_disabled.md":"DZQTGE3r","fr-fr_schema_meta_hidden.md":"CH641WGJ","fr-fr_schema_meta_nested.md":"CXg161IJ","fr-fr_schema_meta_required.md":"AMry9egd","fr-fr_schema_meta_role.md":"D8AVOO2q","ja-jp_about_community.md":"JrFBswvt","ja-jp_about_contact.md":"B0-O4S_i","ja-jp_about_contribute_docs.md":"DXWE-8vN","ja-jp_about_contribute_structure.md":"BRLvjrio","ja-jp_about_events.md":"C6Lbkdzy","ja-jp_about_faq.md":"BHvcGDdX","ja-jp_about_history.md":"D6bXtCIl","ja-jp_about_license.md":"Dl4-WXLp","ja-jp_about_migration.md":"CYesbht5","ja-jp_about_releases.md":"dxqn56pI","ja-jp_about_releases_v4.1.md":"D-4mv0eD","ja-jp_about_releases_v4.10.md":"CQU6TiUI","ja-jp_about_releases_v4.11.md":"Cpe6TVM5","ja-jp_about_releases_v4.12.md":"Dgz3Hxzi","ja-jp_about_releases_v4.13.md":"CExbxAEO","ja-jp_about_releases_v4.14.md":"-LHdTizG","ja-jp_about_releases_v4.15.md":"CsU5Gvy2","ja-jp_about_releases_v4.2.md":"DVAbDj0E","ja-jp_about_releases_v4.3.md":"rNedXIOI","ja-jp_about_releases_v4.4.md":"97NY8zcR","ja-jp_about_releases_v4.5.md":"B96XwbJ-","ja-jp_about_releases_v4.6.md":"jy0Ybm0U","ja-jp_about_releases_v4.7.md":"BMuQ5XEp","ja-jp_about_releases_v4.8.md":"DSR-367e","ja-jp_about_releases_v4.9.md":"YI0OX_ln","ja-jp_about_team.md":"Csuo1EWU","ja-jp_about_upgrade.md":"BQgbLqa7","ja-jp_api_console_component.md":"DTst_FTh","ja-jp_api_console_composition.md":"BD9kFK_R","ja-jp_api_console_context.md":"DBIKzjDF","ja-jp_api_console_server.md":"BuqKhkCi","ja-jp_api_core_adapter.md":"CupbmgZS","ja-jp_api_core_app.md":"DNey8cY_","ja-jp_api_core_bot.md":"BAYsJtau","ja-jp_api_core_command.md":"mdGDkTPv","ja-jp_api_core_context.md":"DH96YUg4","ja-jp_api_core_events.md":"itLYR1Zx","ja-jp_api_core_session.md":"DjVjl4Nl","ja-jp_api_database_built-in.md":"BkV3Ime1","ja-jp_api_database_database.md":"BVjUH2io","ja-jp_api_database_evaluation.md":"DuampEDz","ja-jp_api_database_model.md":"B21euBD4","ja-jp_api_database_query.md":"Bh-cCrKp","ja-jp_api_database_selection.md":"Dgw3bswC","ja-jp_api_glossary.md":"Bbfk2L1O","ja-jp_api_index.md":"YnNv4cnf","ja-jp_api_message_api.md":"lSGYnS9G","ja-jp_api_message_components.md":"sg-6iLrl","ja-jp_api_message_elements.md":"Cm3F0uR1","ja-jp_api_message_encoder.md":"G5V0N_Dr","ja-jp_api_message_syntax.md":"tZ1tl2xr","ja-jp_api_platform_channel.md":"Bb9PLDr-","ja-jp_api_platform_guild.md":"Cev2II91","ja-jp_api_platform_member.md":"CFdxtlej","ja-jp_api_platform_message.md":"CrzA9aoe","ja-jp_api_platform_reaction.md":"uoju28v9","ja-jp_api_platform_role.md":"zGDrObT7","ja-jp_api_platform_user.md":"2LI9QKxZ","ja-jp_api_resources_channel.md":"BvwBGVSo","ja-jp_api_resources_guild.md":"BYC4AGXv","ja-jp_api_resources_interaction.md":"DQtJlG_4","ja-jp_api_resources_login.md":"D2dHgwKP","ja-jp_api_resources_member.md":"DR9ocjNf","ja-jp_api_resources_message.md":"f1X0gDuZ","ja-jp_api_resources_reaction.md":"IqXzQ0GW","ja-jp_api_resources_role.md":"F71CauAz","ja-jp_api_resources_user.md":"LNeg9kHu","ja-jp_api_service_bots.md":"BfWtyGEy","ja-jp_api_service_events.md":"CFEFnXBU","ja-jp_api_service_filter.md":"CF9IfAcP","ja-jp_api_service_http.md":"ZRCOvoBI","ja-jp_api_service_i18n.md":"CSiJLtgG","ja-jp_api_service_lifecycle.md":"BE3Pk9Ct","ja-jp_api_service_loader.md":"Bl12intN","ja-jp_api_service_logger.md":"D2itf6Md","ja-jp_api_service_permissions.md":"DlEch0uS","ja-jp_api_service_registry.md":"ByFQoh1P","ja-jp_api_service_router.md":"ByDiCt-B","ja-jp_api_service_selector.md":"BikS5Adg","ja-jp_api_utils_logger.md":"DE5LDejg","ja-jp_api_utils_misc.md":"C8ookKHY","ja-jp_api_utils_observer.md":"8wJ6p_4t","ja-jp_api_utils_random.md":"B15lmdVJ","ja-jp_api_utils_schema.md":"Blxt4agu","ja-jp_cookbook_appendix_commands.md":"gXzWYQoP","ja-jp_cookbook_assets.md":"D3_bwqEJ","ja-jp_cookbook_design_bundle.md":"DIMgPXE_","ja-jp_cookbook_design_disposable.md":"DUG3Rjik","ja-jp_cookbook_design_framework.md":"CljfYHL8","ja-jp_cookbook_design_reversible.md":"BB-DJwTf","ja-jp_cookbook_design_storage.md":"a5NjI8N2","ja-jp_cookbook_design_structure.md":"Cr6OFM1M","ja-jp_cookbook_design_workspace.md":"5LY-ZALq","ja-jp_cookbook_index.md":"DQcxfCet","ja-jp_cookbook_message.md":"BjSTr6U_","ja-jp_cookbook_online.md":"fvQm_MB8","ja-jp_cookbook_practice_assets.md":"BZxrylD_","ja-jp_cookbook_practice_bundle.md":"CC3dJr-Q","ja-jp_cookbook_practice_online.md":"BaVUVSa7","ja-jp_cookbook_practice_render.md":"C27KOTz7","ja-jp_cookbook_practice_testing.md":"Br5Kl9dI","ja-jp_cookbook_render.md":"Dom0lx35","ja-jp_cookbook_storage.md":"8M5OpABa","ja-jp_cookbook_testing.md":"1ktX0it-","ja-jp_guide_adapter_adapter.md":"CF3_gKaj","ja-jp_guide_adapter_bot.md":"CiLzm-vp","ja-jp_guide_adapter_index.md":"CH78-okE","ja-jp_guide_adapter_integration.md":"DOH59w9b","ja-jp_guide_adapter_message.md":"DUB_eONs","ja-jp_guide_basic_advanced.md":"BiZXPGJO","ja-jp_guide_basic_command.md":"C3EH4Wqr","ja-jp_guide_basic_element.md":"BCHQcWEU","ja-jp_guide_basic_events.md":"3acswKhl","ja-jp_guide_basic_middleware.md":"DffNoFoA","ja-jp_guide_console_client.md":"IvCWK7nq","ja-jp_guide_console_data.md":"DcPjzZcu","ja-jp_guide_console_index.md":"CypLy0vW","ja-jp_guide_console_theme.md":"DsucER1F","ja-jp_guide_database_builtin.md":"BrNC0E-G","ja-jp_guide_database_index.md":"DBthgkkP","ja-jp_guide_database_model.md":"CpEPEFVx","ja-jp_guide_database_observer.md":"DK2O_H6M","ja-jp_guide_database_permission.md":"CQTvDxYY","ja-jp_guide_database_select.md":"DdQ6PB-p","ja-jp_guide_database_selection.md":"DYFt4FDy","ja-jp_guide_database_writing.md":"ZCCXB8qE","ja-jp_guide_develop_config.md":"DlUU0-ic","ja-jp_guide_develop_publish.md":"CbV8iaPk","ja-jp_guide_develop_script.md":"DeHCGJfp","ja-jp_guide_develop_setup.md":"CxgIinPs","ja-jp_guide_develop_workspace.md":"CGFir3in","ja-jp_guide_i18n_crowdin.md":"_SV-uRuq","ja-jp_guide_i18n_index.md":"CTtP69DO","ja-jp_guide_i18n_lang-pack.md":"CgT1In8Q","ja-jp_guide_i18n_presets.md":"DYY5vZP2","ja-jp_guide_i18n_translation.md":"BFVw0O7s","ja-jp_guide_index.md":"CsOuqhdU","ja-jp_guide_plugin_filter.md":"DXmBJ3W1","ja-jp_guide_plugin_index.md":"BlWBcC-m","ja-jp_guide_plugin_lifecycle.md":"DF1ei8j7","ja-jp_guide_plugin_schema.md":"COjllUgp","ja-jp_guide_plugin_selector.md":"DAfqvpBM","ja-jp_guide_plugin_service.md":"BLBx7a12","ja-jp_index.md":"WY2l2GtZ","ja-jp_manual_faq.md":"Cek48J8M","ja-jp_manual_introduction.md":"B-tb8LCu","ja-jp_manual_launcher_cli.md":"BDw6JPrG","ja-jp_manual_launcher_system.md":"hlM1yOBz","ja-jp_manual_recipe_dataview.md":"a95QGeWc","ja-jp_manual_recipe_execution.md":"Dv7s9oLt","ja-jp_manual_recipe_multiple.md":"9l1EuOhh","ja-jp_manual_recipe_search.md":"D-x8WZS2","ja-jp_manual_recipe_server.md":"BBM5bZHV","ja-jp_manual_starter_android.md":"BkKfchnW","ja-jp_manual_starter_boilerplate.md":"CAoE0FXo","ja-jp_manual_starter_direct.md":"DA-fLhCy","ja-jp_manual_starter_docker.md":"DBITfMiB","ja-jp_manual_starter_index.md":"BkekWesq","ja-jp_manual_starter_linux.md":"C7xfCyY4","ja-jp_manual_starter_macos.md":"uboeOoZs","ja-jp_manual_starter_windows.md":"BSY4_ikn","ja-jp_manual_usage_adapter.md":"Bnn_9P9x","ja-jp_manual_usage_command.md":"C0dInDvW","ja-jp_manual_usage_customize.md":"DUKpUDY9","ja-jp_manual_usage_market.md":"CUokQh15","ja-jp_manual_usage_platform.md":"CHOAa_pi","ja-jp_market_index.md":"Dy2oP3EI","ja-jp_market_service.md":"ldFbPolG","ja-jp_plugins_adapter_dingtalk.md":"Buy2DLOr","ja-jp_plugins_adapter_discord.md":"DXt2FIvO","ja-jp_plugins_adapter_kook.md":"CJFMp5vi","ja-jp_plugins_adapter_lark.md":"D2Fa9-G6","ja-jp_plugins_adapter_line.md":"BQyL8HHh","ja-jp_plugins_adapter_mail.md":"DaijKZ7u","ja-jp_plugins_adapter_matrix.md":"Ce3v8UJy","ja-jp_plugins_adapter_onebot.md":"ChOmWcj9","ja-jp_plugins_adapter_qq.md":"CIIs6AWx","ja-jp_plugins_adapter_qqguild.md":"BhIdLWlf","ja-jp_plugins_adapter_satori.md":"Aa1eNkcu","ja-jp_plugins_adapter_slack.md":"VWIyIE97","ja-jp_plugins_adapter_telegram.md":"CC23g7kz","ja-jp_plugins_adapter_wechat-official.md":"CeZNuM5l","ja-jp_plugins_adapter_wecom.md":"D4tdiIup","ja-jp_plugins_adapter_whatsapp.md":"Cw9MWZ-U","ja-jp_plugins_adapter_zulip.md":"DnmWRfbt","ja-jp_plugins_common_admin.md":"DQcENRVp","ja-jp_plugins_common_bind.md":"BHNwOqjl","ja-jp_plugins_common_broadcast.md":"BIy19EAp","ja-jp_plugins_common_callme.md":"CoUTT-lB","ja-jp_plugins_common_echo.md":"DeI9wX13","ja-jp_plugins_common_help.md":"D4oM5snS","ja-jp_plugins_common_inspect.md":"B09VUec5","ja-jp_plugins_common_rate-limit.md":"BOJ_iFAS","ja-jp_plugins_console_analytics.md":"Cs2UL6MV","ja-jp_plugins_console_auth.md":"CokjHXX-","ja-jp_plugins_console_commands.md":"CS9h93Dl","ja-jp_plugins_console_config.md":"BcWg-qDI","ja-jp_plugins_console_dataview.md":"CL1oOotl","ja-jp_plugins_console_explorer.md":"CZsTZ5rh","ja-jp_plugins_console_index.md":"CIBsq4z9","ja-jp_plugins_console_insight.md":"CosE68fc","ja-jp_plugins_console_locales.md":"C-mlY3RY","ja-jp_plugins_console_logger.md":"DENLI8Jj","ja-jp_plugins_console_login.md":"B4fP-uFV","ja-jp_plugins_console_market.md":"5Ml4Hb6e","ja-jp_plugins_console_sandbox.md":"BNawxn7V","ja-jp_plugins_console_status.md":"DLhw2kZn","ja-jp_plugins_database_memory.md":"CTHH0O3b","ja-jp_plugins_database_mongo.md":"BXwp_hdY","ja-jp_plugins_database_mysql.md":"D4Vo9SDO","ja-jp_plugins_database_postgres.md":"Dq1Xfw-2","ja-jp_plugins_database_sqlite.md":"BVefUGvh","ja-jp_plugins_develop_hmr.md":"CJ1My9le","ja-jp_plugins_develop_mock.md":"Crme7TZw","ja-jp_plugins_develop_server-proxy.md":"DbGRp6z2","ja-jp_plugins_develop_server-satori.md":"DHjunatZ","ja-jp_plugins_develop_server-temp.md":"ClPiK43a","ja-jp_plugins_develop_server.md":"BUXFP9To","ja-jp_plugins_index.md":"D0meslYn","ja-jp_releases_index.md":"Dyg1B5pL","ja-jp_releases_v4.1.md":"DrDQTet3","ja-jp_releases_v4.10.md":"Spz-Icym","ja-jp_releases_v4.11.md":"B6A_j22Y","ja-jp_releases_v4.12.md":"D3yUJmku","ja-jp_releases_v4.13.md":"C37xzmX3","ja-jp_releases_v4.14.md":"BX-zydSB","ja-jp_releases_v4.15.md":"Byrn6fE5","ja-jp_releases_v4.2.md":"vnWKmGY2","ja-jp_releases_v4.3.md":"M1vHfvNA","ja-jp_releases_v4.4.md":"BtjPXKeM","ja-jp_releases_v4.5.md":"BA_5pvRd","ja-jp_releases_v4.6.md":"BatnBRS9","ja-jp_releases_v4.7.md":"CamKLzol","ja-jp_releases_v4.8.md":"AsV76EsS","ja-jp_releases_v4.9.md":"HLjbgfAJ","ja-jp_schema_advanced_computed.md":"CzEqaAPZ","ja-jp_schema_advanced_dynamic.md":"DtS4MaWP","ja-jp_schema_advanced_intersect.md":"Dg1xzO76","ja-jp_schema_advanced_transform.md":"CPnhadJF","ja-jp_schema_advanced_union-arbitrary.md":"CuGGWHkR","ja-jp_schema_advanced_union-select.md":"OYM9ZKNg","ja-jp_schema_advanced_union-tagged-1.md":"CMkEPAOA","ja-jp_schema_advanced_union-tagged-2.md":"C-oIxEmK","ja-jp_schema_basic_array.md":"C1O5ggg2","ja-jp_schema_basic_bitset.md":"Bzr4gP-L","ja-jp_schema_basic_boolean.md":"Bv5fEy5T","ja-jp_schema_basic_date.md":"B5NachhX","ja-jp_schema_basic_dict.md":"ClQrg2sA","ja-jp_schema_basic_number.md":"UE46J0EM","ja-jp_schema_basic_object.md":"LmTfhUlG","ja-jp_schema_basic_path.md":"BTwKuKIy","ja-jp_schema_basic_string.md":"NgN3br_o","ja-jp_schema_basic_tuple.md":"wu0x7MMZ","ja-jp_schema_index.md":"Dr3IBNtL","ja-jp_schema_meta_default.md":"C5KyxGFP","ja-jp_schema_meta_description.md":"38aRuZ-s","ja-jp_schema_meta_disabled.md":"z_dqQoVn","ja-jp_schema_meta_hidden.md":"egVhxCdw","ja-jp_schema_meta_nested.md":"BCi0GwqU","ja-jp_schema_meta_required.md":"CZi-rMWP","ja-jp_schema_meta_role.md":"DyK6RFhH","readme.md":"h5bDCSAC","ru-ru_about_community.md":"B5nqdDAl","ru-ru_about_contact.md":"dBlYs5i8","ru-ru_about_contribute_docs.md":"BHz3RxqF","ru-ru_about_contribute_structure.md":"Bxn9tBUn","ru-ru_about_events.md":"DAi9mdzY","ru-ru_about_faq.md":"C88VNyzo","ru-ru_about_history.md":"DTlp5DsO","ru-ru_about_license.md":"DMg88Yzx","ru-ru_about_migration.md":"DiUaZ-vQ","ru-ru_about_releases.md":"PJymm-69","ru-ru_about_releases_v4.1.md":"BgDcPm4Q","ru-ru_about_releases_v4.10.md":"F_v0-pu7","ru-ru_about_releases_v4.11.md":"ZT9FbELS","ru-ru_about_releases_v4.12.md":"CiOrSUK-","ru-ru_about_releases_v4.13.md":"D06BIHZN","ru-ru_about_releases_v4.14.md":"ChPrUddJ","ru-ru_about_releases_v4.15.md":"DFbv3Ro9","ru-ru_about_releases_v4.2.md":"DEDG-MFo","ru-ru_about_releases_v4.3.md":"BUF9sGFQ","ru-ru_about_releases_v4.4.md":"Bpgb-BJK","ru-ru_about_releases_v4.5.md":"t6q_Pn3k","ru-ru_about_releases_v4.6.md":"DP2-q-zx","ru-ru_about_releases_v4.7.md":"TiyILbRO","ru-ru_about_releases_v4.8.md":"DNEWXi-w","ru-ru_about_releases_v4.9.md":"CsS3Wlrj","ru-ru_about_team.md":"BpRUBdRr","ru-ru_about_upgrade.md":"BtiMgAtB","ru-ru_api_console_component.md":"BijFxyLx","ru-ru_api_console_composition.md":"J7BgA4Sr","ru-ru_api_console_context.md":"Cpn9HjVD","ru-ru_api_console_server.md":"DGJXLODu","ru-ru_api_core_adapter.md":"Be-P_Ud5","ru-ru_api_core_app.md":"6wQImqZ2","ru-ru_api_core_bot.md":"CoMfXYSr","ru-ru_api_core_command.md":"iCn8lAS7","ru-ru_api_core_context.md":"C28JU_92","ru-ru_api_core_events.md":"BnNRBABH","ru-ru_api_core_session.md":"ceA-9GPk","ru-ru_api_database_built-in.md":"BBl-yWo8","ru-ru_api_database_database.md":"DDaJRQn1","ru-ru_api_database_evaluation.md":"BFPKXYVe","ru-ru_api_database_model.md":"D8LPLoWM","ru-ru_api_database_query.md":"OBMDFpAa","ru-ru_api_database_selection.md":"DZzJlNx1","ru-ru_api_glossary.md":"Q52n33lW","ru-ru_api_index.md":"GXhZ4sz2","ru-ru_api_message_api.md":"7qX6JRBA","ru-ru_api_message_components.md":"B-mTOGfi","ru-ru_api_message_elements.md":"D2-VjBPm","ru-ru_api_message_encoder.md":"zTp7oLH1","ru-ru_api_message_syntax.md":"DWRJyNCh","ru-ru_api_platform_channel.md":"CdGLMUfc","ru-ru_api_platform_guild.md":"CrwGWmk4","ru-ru_api_platform_member.md":"B3DiDgyN","ru-ru_api_platform_message.md":"DUexBEnP","ru-ru_api_platform_reaction.md":"CRJE2wEU","ru-ru_api_platform_role.md":"BWVXEIDj","ru-ru_api_platform_user.md":"CfRX4cZW","ru-ru_api_resources_channel.md":"BdmYToG7","ru-ru_api_resources_guild.md":"CnF4ipn5","ru-ru_api_resources_interaction.md":"CfrUo7YI","ru-ru_api_resources_login.md":"CstbhSRT","ru-ru_api_resources_member.md":"s-r5CGbn","ru-ru_api_resources_message.md":"DEXmW7pB","ru-ru_api_resources_reaction.md":"DRft7mTO","ru-ru_api_resources_role.md":"CWinIe4v","ru-ru_api_resources_user.md":"BZI6Wj8V","ru-ru_api_service_bots.md":"D42mU3Uu","ru-ru_api_service_events.md":"DeAFrgSe","ru-ru_api_service_filter.md":"CL2AjJ7E","ru-ru_api_service_http.md":"CNQf6rEH","ru-ru_api_service_i18n.md":"DcRVnA6O","ru-ru_api_service_lifecycle.md":"L2tfLD3d","ru-ru_api_service_loader.md":"13uK8gVv","ru-ru_api_service_logger.md":"CsJPKAN9","ru-ru_api_service_permissions.md":"Bw4JCLaF","ru-ru_api_service_registry.md":"YbrXaCP7","ru-ru_api_service_router.md":"DfRonhGl","ru-ru_api_service_selector.md":"9rXh9Gj5","ru-ru_api_utils_logger.md":"-7lZJzQL","ru-ru_api_utils_misc.md":"Bq_-OqBB","ru-ru_api_utils_observer.md":"Bl62JLRc","ru-ru_api_utils_random.md":"BkJUi6uF","ru-ru_api_utils_schema.md":"lc2NtlFd","ru-ru_cookbook_appendix_commands.md":"C2LEaOSp","ru-ru_cookbook_assets.md":"C6PoX7ZO","ru-ru_cookbook_design_bundle.md":"BcLrq54t","ru-ru_cookbook_design_disposable.md":"BMjUHc69","ru-ru_cookbook_design_framework.md":"BRGjtDy-","ru-ru_cookbook_design_reversible.md":"BypKqWzJ","ru-ru_cookbook_design_storage.md":"BR-XgL0O","ru-ru_cookbook_design_structure.md":"C6m2N9vU","ru-ru_cookbook_design_workspace.md":"DWwjsItx","ru-ru_cookbook_index.md":"C48ixFhU","ru-ru_cookbook_message.md":"DR1veTmi","ru-ru_cookbook_online.md":"BHvDpwEm","ru-ru_cookbook_practice_assets.md":"80vnv8j0","ru-ru_cookbook_practice_bundle.md":"JTkqjs7k","ru-ru_cookbook_practice_online.md":"BiBEDVaJ","ru-ru_cookbook_practice_render.md":"yP2YMXKr","ru-ru_cookbook_practice_testing.md":"UoxDH6Df","ru-ru_cookbook_render.md":"B45F0qrI","ru-ru_cookbook_storage.md":"BsIo-6LK","ru-ru_cookbook_testing.md":"CagdtPZO","ru-ru_guide_adapter_adapter.md":"Bgnc9qLa","ru-ru_guide_adapter_bot.md":"BVgY5jHh","ru-ru_guide_adapter_index.md":"BLU-T8EJ","ru-ru_guide_adapter_integration.md":"Dvs6gK-9","ru-ru_guide_adapter_message.md":"DEXGnbvY","ru-ru_guide_basic_advanced.md":"a3kTdrA4","ru-ru_guide_basic_command.md":"CkUNdEUi","ru-ru_guide_basic_element.md":"V_1hPZsS","ru-ru_guide_basic_events.md":"DbdZNLcr","ru-ru_guide_basic_middleware.md":"Cabkyh3q","ru-ru_guide_console_client.md":"B-JNqXiJ","ru-ru_guide_console_data.md":"BZix82c-","ru-ru_guide_console_index.md":"DdH6d2jJ","ru-ru_guide_console_theme.md":"DbbAQFcr","ru-ru_guide_database_builtin.md":"DKqAXzMK","ru-ru_guide_database_index.md":"Cd_JMA6H","ru-ru_guide_database_model.md":"Do_Whcdr","ru-ru_guide_database_observer.md":"CkVLMXsU","ru-ru_guide_database_permission.md":"DOnyTKqY","ru-ru_guide_database_select.md":"BQnBhEKL","ru-ru_guide_database_selection.md":"QV_RaM6W","ru-ru_guide_database_writing.md":"K9wrIQeF","ru-ru_guide_develop_config.md":"cB-SVUp8","ru-ru_guide_develop_publish.md":"BrcQm-XM","ru-ru_guide_develop_script.md":"D56j8tTX","ru-ru_guide_develop_setup.md":"CV3bg94A","ru-ru_guide_develop_workspace.md":"D-tgofDk","ru-ru_guide_i18n_crowdin.md":"C5wbboQ4","ru-ru_guide_i18n_index.md":"JG4Odp2v","ru-ru_guide_i18n_lang-pack.md":"CYiraY7X","ru-ru_guide_i18n_presets.md":"DSeJnN__","ru-ru_guide_i18n_translation.md":"CXN50OYU","ru-ru_guide_index.md":"lv8k08DD","ru-ru_guide_plugin_filter.md":"DqswPkL6","ru-ru_guide_plugin_index.md":"DuTtoFRN","ru-ru_guide_plugin_lifecycle.md":"DNQn7TCV","ru-ru_guide_plugin_schema.md":"DIkMp2CN","ru-ru_guide_plugin_selector.md":"DSY9PXj_","ru-ru_guide_plugin_service.md":"ClPZoyJ6","ru-ru_index.md":"CJkiumlh","ru-ru_manual_faq.md":"Bl1AypxV","ru-ru_manual_introduction.md":"fW4rENpv","ru-ru_manual_launcher_cli.md":"CLWqX02w","ru-ru_manual_launcher_system.md":"C5BS8xGP","ru-ru_manual_recipe_dataview.md":"Bmc3zQB_","ru-ru_manual_recipe_execution.md":"Bjz764O5","ru-ru_manual_recipe_multiple.md":"Dmv9qmk7","ru-ru_manual_recipe_search.md":"BJ8QZu6x","ru-ru_manual_recipe_server.md":"C0FHVKPd","ru-ru_manual_starter_android.md":"BRrP8DOi","ru-ru_manual_starter_boilerplate.md":"Bv_IXogd","ru-ru_manual_starter_direct.md":"BvV_ru4N","ru-ru_manual_starter_docker.md":"CGBNUu2C","ru-ru_manual_starter_index.md":"Ln1vEf_2","ru-ru_manual_starter_linux.md":"D71GaXhR","ru-ru_manual_starter_macos.md":"CQHKUE8Y","ru-ru_manual_starter_windows.md":"CvMTeVQC","ru-ru_manual_usage_adapter.md":"DsciKfYY","ru-ru_manual_usage_command.md":"X5O-m23e","ru-ru_manual_usage_customize.md":"g7AbAAbf","ru-ru_manual_usage_market.md":"5ZU7BIEo","ru-ru_manual_usage_platform.md":"fqLLLJaJ","ru-ru_market_index.md":"C0lkHV6N","ru-ru_market_service.md":"3Q5PvwZy","ru-ru_plugins_adapter_dingtalk.md":"ClGV4APb","ru-ru_plugins_adapter_discord.md":"BwyXOCn4","ru-ru_plugins_adapter_kook.md":"BRYEGHhs","ru-ru_plugins_adapter_lark.md":"NFKezBiy","ru-ru_plugins_adapter_line.md":"Da2wZRRB","ru-ru_plugins_adapter_mail.md":"Bl5OmCD_","ru-ru_plugins_adapter_matrix.md":"B8ZrFrUI","ru-ru_plugins_adapter_onebot.md":"BDsB6YMp","ru-ru_plugins_adapter_qq.md":"jVsH4L1H","ru-ru_plugins_adapter_qqguild.md":"DH4iQ4P2","ru-ru_plugins_adapter_satori.md":"Bgea3T4U","ru-ru_plugins_adapter_slack.md":"BDsq6Ohk","ru-ru_plugins_adapter_telegram.md":"Dl4BxxSH","ru-ru_plugins_adapter_wechat-official.md":"D8b6W-SO","ru-ru_plugins_adapter_wecom.md":"LGqSw2vr","ru-ru_plugins_adapter_whatsapp.md":"B4C1dMZ-","ru-ru_plugins_adapter_zulip.md":"DLtGzYZE","ru-ru_plugins_common_admin.md":"HZtK5Je0","ru-ru_plugins_common_bind.md":"A_2sK_Ff","ru-ru_plugins_common_broadcast.md":"DcNjo6NY","ru-ru_plugins_common_callme.md":"ifjPMomV","ru-ru_plugins_common_echo.md":"BSv7oMjN","ru-ru_plugins_common_help.md":"DHn-nSVk","ru-ru_plugins_common_inspect.md":"BgUKrNSJ","ru-ru_plugins_common_rate-limit.md":"DRk1jS-X","ru-ru_plugins_console_analytics.md":"DINFdKnu","ru-ru_plugins_console_auth.md":"cha9Jm2e","ru-ru_plugins_console_commands.md":"CD2tAl5x","ru-ru_plugins_console_config.md":"DXs8eP0e","ru-ru_plugins_console_dataview.md":"MmpU_6fX","ru-ru_plugins_console_explorer.md":"BUa_4gy6","ru-ru_plugins_console_index.md":"Ds2D2Z_a","ru-ru_plugins_console_insight.md":"COMuVMWt","ru-ru_plugins_console_locales.md":"CDsNqfQ_","ru-ru_plugins_console_logger.md":"i4j8hAse","ru-ru_plugins_console_login.md":"LkE3IeeE","ru-ru_plugins_console_market.md":"DqBpPXfb","ru-ru_plugins_console_sandbox.md":"DSX0jJMm","ru-ru_plugins_console_status.md":"Dla99tWS","ru-ru_plugins_database_memory.md":"BYLRmgcI","ru-ru_plugins_database_mongo.md":"CRldpqW-","ru-ru_plugins_database_mysql.md":"CRaCJPXq","ru-ru_plugins_database_postgres.md":"B8x-HSrD","ru-ru_plugins_database_sqlite.md":"eeoBtI2Y","ru-ru_plugins_develop_hmr.md":"CwrO-sm0","ru-ru_plugins_develop_mock.md":"BAjhc1_v","ru-ru_plugins_develop_server-proxy.md":"ir9lCNT3","ru-ru_plugins_develop_server-satori.md":"gOidHEFH","ru-ru_plugins_develop_server-temp.md":"mHNbFbxb","ru-ru_plugins_develop_server.md":"CcWOrV5H","ru-ru_plugins_index.md":"C5W8f_Od","ru-ru_releases_index.md":"CelNt1Z_","ru-ru_releases_v4.1.md":"cwkENZJ9","ru-ru_releases_v4.10.md":"ndytuAAH","ru-ru_releases_v4.11.md":"DfcKqciN","ru-ru_releases_v4.12.md":"D7_bcQeM","ru-ru_releases_v4.13.md":"Db9O_k-F","ru-ru_releases_v4.14.md":"o6KYguL_","ru-ru_releases_v4.15.md":"a79eE7co","ru-ru_releases_v4.2.md":"B5oKSTbn","ru-ru_releases_v4.3.md":"DGwsRoGF","ru-ru_releases_v4.4.md":"BwZ842BT","ru-ru_releases_v4.5.md":"CutxAI-o","ru-ru_releases_v4.6.md":"Ci_4npBT","ru-ru_releases_v4.7.md":"j34gVuRQ","ru-ru_releases_v4.8.md":"DTw74yRA","ru-ru_releases_v4.9.md":"Bzn17_wP","ru-ru_schema_advanced_computed.md":"SElrhXJW","ru-ru_schema_advanced_dynamic.md":"DvISH0qf","ru-ru_schema_advanced_intersect.md":"DEEMsSNL","ru-ru_schema_advanced_transform.md":"Bfy6j52K","ru-ru_schema_advanced_union-arbitrary.md":"ClUvwJ_p","ru-ru_schema_advanced_union-select.md":"i20ew653","ru-ru_schema_advanced_union-tagged-1.md":"DQAcFrgu","ru-ru_schema_advanced_union-tagged-2.md":"oywx1oQ7","ru-ru_schema_basic_array.md":"aorT8USp","ru-ru_schema_basic_bitset.md":"cCQnzRNd","ru-ru_schema_basic_boolean.md":"1CKpWH_g","ru-ru_schema_basic_date.md":"CEo9HjDC","ru-ru_schema_basic_dict.md":"DhT7WDdz","ru-ru_schema_basic_number.md":"C3OLT7xZ","ru-ru_schema_basic_object.md":"Bjl-0h3e","ru-ru_schema_basic_path.md":"CMGK42qO","ru-ru_schema_basic_string.md":"B9VVfRhX","ru-ru_schema_basic_tuple.md":"bb3hlLdg","ru-ru_schema_index.md":"Db7gae34","ru-ru_schema_meta_default.md":"DnodkpBQ","ru-ru_schema_meta_description.md":"qLdLebuv","ru-ru_schema_meta_disabled.md":"DcF_uyJF","ru-ru_schema_meta_hidden.md":"C5IEjmud","ru-ru_schema_meta_nested.md":"n0QBRw1c","ru-ru_schema_meta_required.md":"Cl6P_s1f","ru-ru_schema_meta_role.md":"czHwXDre","zh-cn_about_community.md":"O6UgjstS","zh-cn_about_contact.md":"5gfzCpsd","zh-cn_about_contribute_docs.md":"BOScEC8Q","zh-cn_about_contribute_structure.md":"BPN22_l-","zh-cn_about_events.md":"BoA_DdJg","zh-cn_about_faq.md":"Ctzh7vv6","zh-cn_about_history.md":"Ca1mJ-WQ","zh-cn_about_license.md":"furofVau","zh-cn_about_releases.md":"fJn2J1p3","zh-cn_about_team.md":"DlEPBP6_","zh-cn_about_upgrade.md":"DX0AyEkP","zh-cn_api_console_component.md":"V1Aqxzzp","zh-cn_api_console_composition.md":"BaPDqoEg","zh-cn_api_console_context.md":"DJ5lJkc5","zh-cn_api_console_server.md":"B8pq1_WO","zh-cn_api_core_adapter.md":"B9m7RI3H","zh-cn_api_core_app.md":"Cjg_yzwm","zh-cn_api_core_bot.md":"BlQ9G1Qc","zh-cn_api_core_command.md":"D6y9vFfl","zh-cn_api_core_context.md":"B78mjYUX","zh-cn_api_core_events.md":"DChdll7h","zh-cn_api_core_session.md":"BM4St1V6","zh-cn_api_database_built-in.md":"Cd6paUbs","zh-cn_api_database_database.md":"D63HB2Lx","zh-cn_api_database_evaluation.md":"DnS3guqj","zh-cn_api_database_model.md":"pCBcZTYs","zh-cn_api_database_query.md":"gjxkZ0WT","zh-cn_api_database_selection.md":"Dw3QC3sM","zh-cn_api_glossary.md":"4i8tdcSP","zh-cn_api_index.md":"D_Z3AniQ","zh-cn_api_message_api.md":"C_Rln115","zh-cn_api_message_components.md":"BXqsJPT7","zh-cn_api_message_elements.md":"C5gmaiVp","zh-cn_api_message_encoder.md":"DD4LQCE6","zh-cn_api_message_syntax.md":"DXB8RCV6","zh-cn_api_resources_channel.md":"v3ZJyBwy","zh-cn_api_resources_guild.md":"DMhrkWr2","zh-cn_api_resources_interaction.md":"CC-l35yG","zh-cn_api_resources_login.md":"5VORYY-T","zh-cn_api_resources_member.md":"kGPsERzH","zh-cn_api_resources_message.md":"DfuBz_BD","zh-cn_api_resources_reaction.md":"CZQquvjt","zh-cn_api_resources_role.md":"C35uueMG","zh-cn_api_resources_user.md":"8xRuTeYh","zh-cn_api_service_events.md":"DBb9Rrb8","zh-cn_api_service_filter.md":"YwjocbUN","zh-cn_api_service_http.md":"DUJMyhj2","zh-cn_api_service_i18n.md":"nZn3s5_7","zh-cn_api_service_loader.md":"B6OfDbyo","zh-cn_api_service_permissions.md":"DN6muFB-","zh-cn_api_service_registry.md":"aLn22uxq","zh-cn_api_service_server.md":"CA1cwm3R","zh-cn_api_service_timer.md":"Bv6G3QTI","zh-cn_api_utils_logger.md":"BFtiR3TG","zh-cn_api_utils_misc.md":"BhqRGovs","zh-cn_api_utils_observer.md":"Dk4Hysbr","zh-cn_api_utils_random.md":"DcwyJgRV","zh-cn_api_utils_schema.md":"7QBtkyec","zh-cn_cookbook_appendix_commands.md":"C_7M7wGL","zh-cn_cookbook_design_disposable.md":"za8wW51J","zh-cn_cookbook_design_framework.md":"CaSgwk-O","zh-cn_cookbook_design_storage.md":"DVhiAxcA","zh-cn_cookbook_design_structure.md":"N7XQKTna","zh-cn_cookbook_design_workspace.md":"BO9Ku0Um","zh-cn_cookbook_index.md":"CJBo0igl","zh-cn_cookbook_message.md":"HzcaX6ZS","zh-cn_cookbook_practice_assets.md":"h5NPU3th","zh-cn_cookbook_practice_bundle.md":"D_v6siAh","zh-cn_cookbook_practice_online.md":"Dmy37d2k","zh-cn_cookbook_practice_render.md":"CL2y_4bv","zh-cn_cookbook_practice_testing.md":"Zf6c_FG6","zh-cn_guide_adapter_adapter.md":"BuchdoE2","zh-cn_guide_adapter_bot.md":"CbumTt0a","zh-cn_guide_adapter_index.md":"DqeLTmOs","zh-cn_guide_adapter_integration.md":"Dl645MiI","zh-cn_guide_adapter_message.md":"Bz8eCL2u","zh-cn_guide_basic_advanced.md":"DIzP4cTh","zh-cn_guide_basic_command.md":"CsCCqSpL","zh-cn_guide_basic_element.md":"sleMiF-v","zh-cn_guide_basic_events.md":"B2C3gfXD","zh-cn_guide_basic_middleware.md":"B6JjQpf1","zh-cn_guide_console_client.md":"CWMordFh","zh-cn_guide_console_data.md":"DMrp9y12","zh-cn_guide_console_index.md":"BNSRQcBB","zh-cn_guide_console_theme.md":"C91-vrhF","zh-cn_guide_database_builtin.md":"nJsogyQC","zh-cn_guide_database_index.md":"okmBiW4J","zh-cn_guide_database_model.md":"D7ESF5Q3","zh-cn_guide_database_permission.md":"CYKl9-nc","zh-cn_guide_database_selection.md":"BvDp9DRH","zh-cn_guide_database_writing.md":"ChlsQBNp","zh-cn_guide_develop_config.md":"DE_ggH1S","zh-cn_guide_develop_publish.md":"CKmefJ2D","zh-cn_guide_develop_script.md":"DHPCXIeG","zh-cn_guide_develop_setup.md":"BzsvU4dn","zh-cn_guide_develop_workspace.md":"DmV5l63I","zh-cn_guide_i18n_crowdin.md":"BD41IAAQ","zh-cn_guide_i18n_index.md":"Bk2_-hky","zh-cn_guide_i18n_lang-pack.md":"bWKYLZSU","zh-cn_guide_i18n_translation.md":"BWGbXgxT","zh-cn_guide_index.md":"CgfikOBX","zh-cn_guide_plugin_filter.md":"CMspzJNa","zh-cn_guide_plugin_index.md":"B-tyPRoC","zh-cn_guide_plugin_lifecycle.md":"B95L2q7t","zh-cn_guide_plugin_schema.md":"B6IKlf48","zh-cn_guide_plugin_service.md":"Bo36bdq7","zh-cn_index.md":"D3fF9F_P","zh-cn_manual_faq.md":"DFQ3S5Hs","zh-cn_manual_introduction.md":"D9cdZR8j","zh-cn_manual_launcher_cli.md":"SlA7opZI","zh-cn_manual_launcher_system.md":"nY-rMf49","zh-cn_manual_recipe_execution.md":"bLOma992","zh-cn_manual_recipe_multiple.md":"CNEpsO1m","zh-cn_manual_recipe_search.md":"agy-l7GE","zh-cn_manual_recipe_server.md":"65abJItw","zh-cn_manual_starter_android.md":"Dd_bmMn-","zh-cn_manual_starter_boilerplate.md":"DMIuswDS","zh-cn_manual_starter_direct.md":"UbchXJQI","zh-cn_manual_starter_docker.md":"Bm8TERIP","zh-cn_manual_starter_index.md":"oyoq9g6r","zh-cn_manual_starter_linux.md":"b3kIxIHq","zh-cn_manual_starter_macos.md":"CdPPfA_M","zh-cn_manual_starter_windows.md":"B9j_mmgR","zh-cn_manual_usage_adapter.md":"Cp59vZYa","zh-cn_manual_usage_command.md":"BH7iQrma","zh-cn_manual_usage_customize.md":"CLmbVWe6","zh-cn_manual_usage_market.md":"DogYzYyY","zh-cn_manual_usage_platform.md":"gprB_6JK","zh-cn_market_index.md":"BUfb_IpZ","zh-cn_plugins_adapter_dingtalk.md":"IVNZtBdL","zh-cn_plugins_adapter_discord.md":"CnYhq6aC","zh-cn_plugins_adapter_kook.md":"CYJMvLXT","zh-cn_plugins_adapter_lark.md":"vUfWeByT","zh-cn_plugins_adapter_line.md":"BQst-puo","zh-cn_plugins_adapter_mail.md":"BAfk9DiM","zh-cn_plugins_adapter_matrix.md":"3QPbEPMi","zh-cn_plugins_adapter_qq.md":"Df-ihVib","zh-cn_plugins_adapter_satori.md":"DFLQ4_s0","zh-cn_plugins_adapter_slack.md":"CXE2SI19","zh-cn_plugins_adapter_telegram.md":"Ds8vqbGr","zh-cn_plugins_adapter_wechat-official.md":"DFFJiTwH","zh-cn_plugins_adapter_wecom.md":"BJ1F0Jfp","zh-cn_plugins_adapter_whatsapp.md":"DodpukZX","zh-cn_plugins_adapter_zulip.md":"CM1_wiQr","zh-cn_plugins_common_admin.md":"rn7IgJae","zh-cn_plugins_common_bind.md":"Ca4DPufS","zh-cn_plugins_common_broadcast.md":"DadguvLW","zh-cn_plugins_common_callme.md":"CyRVd2Wo","zh-cn_plugins_common_echo.md":"D44cQOeW","zh-cn_plugins_common_help.md":"DVOeyLrQ","zh-cn_plugins_common_inspect.md":"DGATxLPl","zh-cn_plugins_console_analytics.md":"bR3O2bxI","zh-cn_plugins_console_auth.md":"DHKXsHG4","zh-cn_plugins_console_commands.md":"DIMfzLtD","zh-cn_plugins_console_config.md":"DGhWCDYG","zh-cn_plugins_console_explorer.md":"CUOsxKQ1","zh-cn_plugins_console_index.md":"DD7ussA4","zh-cn_plugins_console_insight.md":"mkdijf0u","zh-cn_plugins_console_locales.md":"BP_6e0JE","zh-cn_plugins_console_logger.md":"C121to2B","zh-cn_plugins_console_market.md":"BHzP8Y-w","zh-cn_plugins_console_sandbox.md":"CKIbEL0W","zh-cn_plugins_console_status.md":"C7Ge5tcZ","zh-cn_plugins_database_memory.md":"Bc4i_Ywr","zh-cn_plugins_database_mongo.md":"CeOyJ0q2","zh-cn_plugins_database_mysql.md":"CiCTj7-x","zh-cn_plugins_database_postgres.md":"DYN9znkV","zh-cn_plugins_database_sqlite.md":"0QykTvOo","zh-cn_plugins_develop_hmr.md":"CXPy-ujo","zh-cn_plugins_develop_http.md":"Vz0r2l3Q","zh-cn_plugins_develop_mock.md":"Bp70jExo","zh-cn_plugins_develop_notifier.md":"_xT4sU6k","zh-cn_plugins_develop_proxy-agent.md":"RaI7E7Op","zh-cn_plugins_develop_server-proxy.md":"BcRxjJ3V","zh-cn_plugins_develop_server-satori.md":"BfmuG584","zh-cn_plugins_develop_server-temp.md":"DFwP7sGF","zh-cn_plugins_develop_server.md":"Be0-x0Wv","zh-cn_plugins_index.md":"Cw24mjch","zh-cn_releases_index.md":"DWL-Bah1","zh-cn_releases_v4.1.md":"C5JpEOKX","zh-cn_releases_v4.10.md":"K6eDqqR6","zh-cn_releases_v4.11.md":"DnQQvBO0","zh-cn_releases_v4.12.md":"D-OHgiXt","zh-cn_releases_v4.13.md":"tW-rxBP7","zh-cn_releases_v4.14.md":"CeWcq5rx","zh-cn_releases_v4.15.md":"BP5hT9UX","zh-cn_releases_v4.2.md":"CmA2Wfif","zh-cn_releases_v4.3.md":"CKufQeaQ","zh-cn_releases_v4.4.md":"ekxFkbRV","zh-cn_releases_v4.5.md":"BpHDQo0m","zh-cn_releases_v4.6.md":"Cg6bppYC","zh-cn_releases_v4.7.md":"Crg4x22R","zh-cn_releases_v4.8.md":"C0OWZhAs","zh-cn_releases_v4.9.md":"C92UESBb","zh-cn_schema_advanced_computed.md":"Ba8J8mIp","zh-cn_schema_advanced_dynamic.md":"DJlF4M8W","zh-cn_schema_advanced_intersect.md":"CJvmfXZj","zh-cn_schema_advanced_transform.md":"DeBrlQea","zh-cn_schema_advanced_union-arbitrary.md":"B_PyLIml","zh-cn_schema_advanced_union-select.md":"CXMtiHUN","zh-cn_schema_advanced_union-tagged-1.md":"CuoTKIpA","zh-cn_schema_advanced_union-tagged-2.md":"BLwvlWDm","zh-cn_schema_basic_array.md":"B4GauPq0","zh-cn_schema_basic_bitset.md":"9252hfIl","zh-cn_schema_basic_boolean.md":"AgjFNtlz","zh-cn_schema_basic_date.md":"CXh2qN9u","zh-cn_schema_basic_dict.md":"Di9xOvZG","zh-cn_schema_basic_number.md":"XIcaUibf","zh-cn_schema_basic_object.md":"DLPPv-9i","zh-cn_schema_basic_path.md":"kwUzGIxD","zh-cn_schema_basic_string.md":"CzVoJooX","zh-cn_schema_basic_tuple.md":"BmWKhiwD","zh-cn_schema_index.md":"Bf8c8PfT","zh-cn_schema_meta_default.md":"DnjsR9Xy","zh-cn_schema_meta_description.md":"8kihDBhC","zh-cn_schema_meta_disabled.md":"nBreZlxz","zh-cn_schema_meta_nested.md":"JeFsqORA","zh-cn_schema_meta_required.md":"V8pV38Oh","zh-cn_schema_meta_role.md":"BEEkSDwW","zh-tw_about_community.md":"Bw55UIW7","zh-tw_about_contact.md":"B-hUglQC","zh-tw_about_contribute_docs.md":"D_pZKGgv","zh-tw_about_contribute_structure.md":"DzJO4CZ5","zh-tw_about_events.md":"BP82EF6i","zh-tw_about_faq.md":"j4u5o-6k","zh-tw_about_history.md":"D19m2q-v","zh-tw_about_license.md":"DzYVUcdU","zh-tw_about_migration.md":"CNlGvTTp","zh-tw_about_releases.md":"CrXeepQU","zh-tw_about_releases_v4.1.md":"Cg0NOQjm","zh-tw_about_releases_v4.10.md":"BYvc4p5R","zh-tw_about_releases_v4.11.md":"CBoIEDXC","zh-tw_about_releases_v4.12.md":"Ca6DXx59","zh-tw_about_releases_v4.13.md":"CiIrlxbN","zh-tw_about_releases_v4.14.md":"B5FcISmg","zh-tw_about_releases_v4.15.md":"BzbLCXLx","zh-tw_about_releases_v4.2.md":"CFGiBvXD","zh-tw_about_releases_v4.3.md":"CDDgPZtc","zh-tw_about_releases_v4.4.md":"Te1ZYjIh","zh-tw_about_releases_v4.5.md":"BpqBT3Ag","zh-tw_about_releases_v4.6.md":"B_fh-drN","zh-tw_about_releases_v4.7.md":"CqDDDiO-","zh-tw_about_releases_v4.8.md":"CZH1cU1x","zh-tw_about_releases_v4.9.md":"DRj7oXk8","zh-tw_about_team.md":"SswCtn37","zh-tw_about_upgrade.md":"CKeM8ox2","zh-tw_api_console_component.md":"D1QJipC8","zh-tw_api_console_composition.md":"BYhrqrN_","zh-tw_api_console_context.md":"Diq2EIQQ","zh-tw_api_console_server.md":"BaHn0UMK","zh-tw_api_core_adapter.md":"DX3TOOMs","zh-tw_api_core_app.md":"B29xlfrJ","zh-tw_api_core_bot.md":"CUY9NpdP","zh-tw_api_core_command.md":"e_AxgCc9","zh-tw_api_core_context.md":"BVFokyVx","zh-tw_api_core_events.md":"DbB2zeRm","zh-tw_api_core_session.md":"BpPcMVwb","zh-tw_api_database_built-in.md":"EKJrDQrN","zh-tw_api_database_database.md":"kjX9f6dn","zh-tw_api_database_evaluation.md":"DcZCx3bR","zh-tw_api_database_model.md":"YVHlU8--","zh-tw_api_database_query.md":"8kBxYhH1","zh-tw_api_database_selection.md":"DJksiNOQ","zh-tw_api_glossary.md":"BevEEIZT","zh-tw_api_index.md":"B-s5qrjD","zh-tw_api_message_api.md":"CVGLSJtv","zh-tw_api_message_components.md":"CFEAgO6o","zh-tw_api_message_elements.md":"BP_48ca5","zh-tw_api_message_encoder.md":"FULuSa3p","zh-tw_api_message_syntax.md":"CPpG9rnl","zh-tw_api_platform_channel.md":"Yk1r2FR9","zh-tw_api_platform_guild.md":"B2xxFImk","zh-tw_api_platform_member.md":"Chax7DeC","zh-tw_api_platform_message.md":"CxagCcBa","zh-tw_api_platform_reaction.md":"DFVD96PZ","zh-tw_api_platform_role.md":"C1LrmxT2","zh-tw_api_platform_user.md":"BsGNr4cd","zh-tw_api_resources_channel.md":"jQX7uFW8","zh-tw_api_resources_guild.md":"DoFNqurL","zh-tw_api_resources_interaction.md":"DduI6a24","zh-tw_api_resources_login.md":"BMt93tj8","zh-tw_api_resources_member.md":"zAfXVtq5","zh-tw_api_resources_message.md":"Bz6W_Cub","zh-tw_api_resources_reaction.md":"5zexPdDb","zh-tw_api_resources_role.md":"IS1fCK0E","zh-tw_api_resources_user.md":"BNyyvd0e","zh-tw_api_service_bots.md":"CSyha-kl","zh-tw_api_service_events.md":"Dx7hY5pe","zh-tw_api_service_filter.md":"zePc8zeL","zh-tw_api_service_http.md":"B_ML3jXH","zh-tw_api_service_i18n.md":"KmHXZN_8","zh-tw_api_service_loader.md":"CBkXCOMo","zh-tw_api_service_logger.md":"BDoade6u","zh-tw_api_service_permissions.md":"DlFJ-Qkf","zh-tw_api_service_registry.md":"CIzBoMBb","zh-tw_api_service_router.md":"DJX98SCw","zh-tw_api_utils_logger.md":"B8vzNStI","zh-tw_api_utils_misc.md":"Be7vYWa3","zh-tw_api_utils_observer.md":"BStzcoPJ","zh-tw_api_utils_random.md":"CxlcHPqF","zh-tw_api_utils_schema.md":"B2VPKltG","zh-tw_cookbook_appendix_commands.md":"C05xUJck","zh-tw_cookbook_assets.md":"BU0kIqzA","zh-tw_cookbook_design_bundle.md":"BDlqRZG6","zh-tw_cookbook_design_disposable.md":"Dco7kA-w","zh-tw_cookbook_design_framework.md":"B9Qqk0ch","zh-tw_cookbook_design_reversible.md":"xHOaeOwV","zh-tw_cookbook_design_storage.md":"4E2ZB_C5","zh-tw_cookbook_design_structure.md":"aMjJDUBd","zh-tw_cookbook_design_workspace.md":"Crc62s0I","zh-tw_cookbook_index.md":"edtlRm_o","zh-tw_cookbook_message.md":"DYk4ooIv","zh-tw_cookbook_online.md":"oY6DWA2z","zh-tw_cookbook_practice_assets.md":"BhCyMzSj","zh-tw_cookbook_practice_bundle.md":"Dw7ogwr9","zh-tw_cookbook_practice_online.md":"CV5RZ7WA","zh-tw_cookbook_practice_render.md":"B4hSZcSL","zh-tw_cookbook_practice_testing.md":"YgkRoYEg","zh-tw_cookbook_render.md":"C7Dmzijx","zh-tw_cookbook_storage.md":"D-g1_SgD","zh-tw_cookbook_testing.md":"Bnx8XNAh","zh-tw_guide_adapter_adapter.md":"BXI7Lsin","zh-tw_guide_adapter_bot.md":"CAofeXhr","zh-tw_guide_adapter_index.md":"WDshk8Jh","zh-tw_guide_adapter_integration.md":"B3Yh8kBT","zh-tw_guide_adapter_message.md":"BW0TKeFo","zh-tw_guide_basic_advanced.md":"BWdOASk0","zh-tw_guide_basic_command.md":"gs2xcFL4","zh-tw_guide_basic_element.md":"BEY9Fp6X","zh-tw_guide_basic_events.md":"BZC-Jx6g","zh-tw_guide_basic_middleware.md":"Di5ExIYN","zh-tw_guide_console_client.md":"BbmoXrM6","zh-tw_guide_console_data.md":"BBIObyLQ","zh-tw_guide_console_index.md":"Cviryfq2","zh-tw_guide_console_theme.md":"A43CeJlz","zh-tw_guide_database_builtin.md":"BARbxMQV","zh-tw_guide_database_index.md":"BB1P0riV","zh-tw_guide_database_model.md":"Cj8owe6V","zh-tw_guide_database_observer.md":"CuwGsfoj","zh-tw_guide_database_permission.md":"DjUiCejF","zh-tw_guide_database_select.md":"D1JPEb8J","zh-tw_guide_database_selection.md":"BHitjgKr","zh-tw_guide_database_writing.md":"CNCH0IbS","zh-tw_guide_develop_config.md":"tptNEn1_","zh-tw_guide_develop_publish.md":"C2lXj3Lr","zh-tw_guide_develop_script.md":"ojGqhiTZ","zh-tw_guide_develop_setup.md":"duyVA8n3","zh-tw_guide_develop_workspace.md":"DtNY3R4T","zh-tw_guide_i18n_crowdin.md":"QHgxSAl2","zh-tw_guide_i18n_index.md":"CSbbZ0Dc","zh-tw_guide_i18n_lang-pack.md":"CANg7_0R","zh-tw_guide_i18n_presets.md":"Be9Q9JJI","zh-tw_guide_i18n_translation.md":"BE3gKoLK","zh-tw_guide_index.md":"CFJ08TvC","zh-tw_guide_plugin_filter.md":"Baq22eNy","zh-tw_guide_plugin_index.md":"CjTJwQfw","zh-tw_guide_plugin_lifecycle.md":"BZGjS1px","zh-tw_guide_plugin_schema.md":"KYuOPS7N","zh-tw_guide_plugin_service.md":"BbRu0tJ_","zh-tw_index.md":"Cgf_NPfV","zh-tw_manual_faq.md":"Cs6Oz1FA","zh-tw_manual_introduction.md":"BHgnxDXS","zh-tw_manual_launcher_cli.md":"ngkMaYN5","zh-tw_manual_launcher_system.md":"CY7oskeN","zh-tw_manual_recipe_dataview.md":"j42Ayben","zh-tw_manual_recipe_execution.md":"WYg8_-xJ","zh-tw_manual_recipe_multiple.md":"COJ8AuV9","zh-tw_manual_recipe_search.md":"DcJf-L3e","zh-tw_manual_recipe_server.md":"DpMH4HUw","zh-tw_manual_starter_android.md":"BXQW40A5","zh-tw_manual_starter_boilerplate.md":"DHDl6P6a","zh-tw_manual_starter_direct.md":"BHD5-x1q","zh-tw_manual_starter_docker.md":"CyUti-a7","zh-tw_manual_starter_index.md":"CSfMhk6r","zh-tw_manual_starter_linux.md":"DPVwTwSP","zh-tw_manual_starter_macos.md":"Dp-NGDP2","zh-tw_manual_starter_windows.md":"Bvj8pkG5","zh-tw_manual_usage_adapter.md":"Ou-E-hIR","zh-tw_manual_usage_command.md":"_jXA53QN","zh-tw_manual_usage_customize.md":"CJCT3CGo","zh-tw_manual_usage_market.md":"DFQhC-a4","zh-tw_manual_usage_platform.md":"5bOPgNIt","zh-tw_market_index.md":"Apn3B57U","zh-tw_market_service.md":"_xY-WHUQ","zh-tw_plugins_adapter_dingtalk.md":"D3a8ZS83","zh-tw_plugins_adapter_discord.md":"BNFwQUes","zh-tw_plugins_adapter_kook.md":"CXI4vdna","zh-tw_plugins_adapter_lark.md":"DoT_bj4E","zh-tw_plugins_adapter_line.md":"DUl7r8Z2","zh-tw_plugins_adapter_mail.md":"CF_tdOLl","zh-tw_plugins_adapter_matrix.md":"BaC3HCBv","zh-tw_plugins_adapter_onebot.md":"DfOnExx7","zh-tw_plugins_adapter_qq.md":"CKoLsvmo","zh-tw_plugins_adapter_qqguild.md":"DO4FHVg5","zh-tw_plugins_adapter_satori.md":"BSP8lKFU","zh-tw_plugins_adapter_slack.md":"DLjhd4li","zh-tw_plugins_adapter_telegram.md":"BYa_tbbH","zh-tw_plugins_adapter_wechat-official.md":"B2gppUu6","zh-tw_plugins_adapter_wecom.md":"-UJEt216","zh-tw_plugins_adapter_whatsapp.md":"D-bju5XP","zh-tw_plugins_adapter_zulip.md":"DT6jkYaH","zh-tw_plugins_common_admin.md":"BHTVMVuK","zh-tw_plugins_common_bind.md":"BCdhqGFU","zh-tw_plugins_common_broadcast.md":"OKSW50Nn","zh-tw_plugins_common_callme.md":"DzoVKeRs","zh-tw_plugins_common_echo.md":"DuMCTinD","zh-tw_plugins_common_help.md":"DNkLrR4j","zh-tw_plugins_common_inspect.md":"CAKk6hgl","zh-tw_plugins_common_rate-limit.md":"B-fHFBzu","zh-tw_plugins_console_analytics.md":"YAL7j5NK","zh-tw_plugins_console_auth.md":"MMtLazbw","zh-tw_plugins_console_commands.md":"DQ74G9Zh","zh-tw_plugins_console_config.md":"3RzyhkLL","zh-tw_plugins_console_dataview.md":"Ce0EplrW","zh-tw_plugins_console_explorer.md":"CcvLu5z3","zh-tw_plugins_console_index.md":"CQLRfvSs","zh-tw_plugins_console_insight.md":"CVVPuup8","zh-tw_plugins_console_locales.md":"BM0PPpDb","zh-tw_plugins_console_logger.md":"Cl5mSFLV","zh-tw_plugins_console_market.md":"BW0wHuT6","zh-tw_plugins_console_sandbox.md":"BUXxPpIj","zh-tw_plugins_console_status.md":"BfIyfQZo","zh-tw_plugins_database_memory.md":"CD-W42kv","zh-tw_plugins_database_mongo.md":"fLQ4miv3","zh-tw_plugins_database_mysql.md":"CH6EqZBy","zh-tw_plugins_database_postgres.md":"5JKtpRH5","zh-tw_plugins_database_sqlite.md":"C8J0UgTv","zh-tw_plugins_develop_hmr.md":"DV0YKHZT","zh-tw_plugins_develop_mock.md":"B8MHqKMc","zh-tw_plugins_develop_server-proxy.md":"eyiva00C","zh-tw_plugins_develop_server-satori.md":"C6_N3OKE","zh-tw_plugins_develop_server-temp.md":"C53rNVe8","zh-tw_plugins_develop_server.md":"DA3mldrN","zh-tw_plugins_index.md":"Bn3So9Wd","zh-tw_releases_index.md":"D0J1pyq-","zh-tw_releases_v4.1.md":"LbV7906X","zh-tw_releases_v4.10.md":"DXDIQELx","zh-tw_releases_v4.11.md":"BmLW7xBM","zh-tw_releases_v4.12.md":"DEudHGPj","zh-tw_releases_v4.13.md":"B-DpWEVS","zh-tw_releases_v4.14.md":"XT-uPAgz","zh-tw_releases_v4.15.md":"CWfqW160","zh-tw_releases_v4.2.md":"BIcYdxcg","zh-tw_releases_v4.3.md":"Cg9-pf-N","zh-tw_releases_v4.4.md":"BByqNfFo","zh-tw_releases_v4.5.md":"BFGcSFkw","zh-tw_releases_v4.6.md":"CbTSgmXw","zh-tw_releases_v4.7.md":"CmrrSln9","zh-tw_releases_v4.8.md":"Dpt51ZMC","zh-tw_releases_v4.9.md":"Rb_0JuGE","zh-tw_schema_advanced_computed.md":"e-33CYDf","zh-tw_schema_advanced_dynamic.md":"y2OfwCQi","zh-tw_schema_advanced_intersect.md":"D9-jA0b6","zh-tw_schema_advanced_transform.md":"BCIq2nbE","zh-tw_schema_advanced_union-arbitrary.md":"C51tajOq","zh-tw_schema_advanced_union-select.md":"Xwm1PxCl","zh-tw_schema_advanced_union-tagged-1.md":"CcD16kTm","zh-tw_schema_advanced_union-tagged-2.md":"D3LKqqnc","zh-tw_schema_basic_array.md":"SpRefMdX","zh-tw_schema_basic_bitset.md":"8dVTUAsd","zh-tw_schema_basic_boolean.md":"DnFzYXAh","zh-tw_schema_basic_date.md":"CodxJg01","zh-tw_schema_basic_dict.md":"DmBlxtk6","zh-tw_schema_basic_number.md":"DfO8hUj5","zh-tw_schema_basic_object.md":"DGY4vtEL","zh-tw_schema_basic_path.md":"Dm63N9YN","zh-tw_schema_basic_string.md":"DujqRksD","zh-tw_schema_basic_tuple.md":"7eYvQKDq","zh-tw_schema_index.md":"Clmr2yMZ","zh-tw_schema_meta_default.md":"Bjhj_igj","zh-tw_schema_meta_description.md":"lVRqF64R","zh-tw_schema_meta_disabled.md":"U-Brh3TQ","zh-tw_schema_meta_hidden.md":"BgjMEEen","zh-tw_schema_meta_nested.md":"BuRrjq7e","zh-tw_schema_meta_required.md":"BfD0C95c","zh-tw_schema_meta_role.md":"xmBc4YX5"}
